{"date":"2021-09-15","players":[{"lastName":"Omar Marmoush","delta":615334,"detailPageLink":"https://www.ligainsider.de/omar-marmoush_20690/","kickbaseId":"2792"},{"lastName":"Suat Serdar","delta":590114,"detailPageLink":"https://www.ligainsider.de/suat-serdar_6225/","kickbaseId":"1790"},{"lastName":"Marco John","delta":462458,"detailPageLink":"https://www.ligainsider.de/marco-john_24130/","kickbaseId":"2927"},{"lastName":"Anton Stach","delta":446249,"detailPageLink":"https://www.ligainsider.de/anton-stach_20696/","kickbaseId":"2987"},{"lastName":"Anderson Lucoqui","delta":418755,"detailPageLink":"https://www.ligainsider.de/anderson-lucoqui_7628/","kickbaseId":"2260"},{"lastName":"Patrick Herrmann","delta":418244,"detailPageLink":"https://www.ligainsider.de/patrick-herrmann_387/","kickbaseId":"547"},{"lastName":"Janik Haberer","delta":412156,"detailPageLink":"https://www.ligainsider.de/janik-haberer_3616/","kickbaseId":"1553"},{"lastName":"Dominik Kohr","delta":406618,"detailPageLink":"https://www.ligainsider.de/dominik-kohr_1821/","kickbaseId":"60"},{"lastName":"Eduard Löwen","delta":399305,"detailPageLink":"https://www.ligainsider.de/eduard-loewen_13671/","kickbaseId":"2254"},{"lastName":"Jonathan Burkardt","delta":395594,"detailPageLink":"https://www.ligainsider.de/jonathan-burkardt_19272/","kickbaseId":"2255"},{"lastName":"Atakan Karazor","delta":394328,"detailPageLink":"https://www.ligainsider.de/atakan-karazor_10442/","kickbaseId":"2214"},{"lastName":"Josuha Guilavogui","delta":392138,"detailPageLink":"https://www.ligainsider.de/josuha-guilavogui_2741/","kickbaseId":"1618"},{"lastName":"Kevin Kampl","delta":386581,"detailPageLink":"https://www.ligainsider.de/kevin-kampl_942/","kickbaseId":"1653"},{"lastName":"Danny Blum","delta":375612,"detailPageLink":"https://www.ligainsider.de/danny-blum_4533/","kickbaseId":"1506"},{"lastName":"Yannik Keitel","delta":374309,"detailPageLink":"https://www.ligainsider.de/yannik-keitel_22010/","kickbaseId":"2764"},{"lastName":"Vladimír Darida","delta":373697,"detailPageLink":"https://www.ligainsider.de/vladimir-darida_2428/","kickbaseId":"748"},{"lastName":"Lucas Tousart","delta":367816,"detailPageLink":"https://www.ligainsider.de/lucas-tousart_12406/","kickbaseId":"2814"},{"lastName":"Konrad Laimer","delta":365961,"detailPageLink":"https://www.ligainsider.de/konrad-laimer_6324/","kickbaseId":"2038"},{"lastName":"Antonios Papadopoulos","delta":361041,"detailPageLink":"https://www.ligainsider.de/antonios-papadopoulos_21190/","kickbaseId":"3050"},{"lastName":"Patrick Wimmer","delta":353351,"detailPageLink":"https://www.ligainsider.de/patrick-wimmer_26236/","kickbaseId":"3124"},{"lastName":"Jeffrey Gouweleeuw","delta":346892,"detailPageLink":"https://www.ligainsider.de/jeffrey-gouweleeuw_1851/","kickbaseId":"1811"},{"lastName":"Michaël Cuisance","delta":343664,"detailPageLink":"https://www.ligainsider.de/michael-cuisance_13818/","kickbaseId":"2057"},{"lastName":"Silas","delta":335950,"detailPageLink":"https://www.ligainsider.de/silas-katompa-mvumpa_21594/","kickbaseId":"2822"},{"lastName":"Sebastiaan Bornauw","delta":335735,"detailPageLink":"https://www.ligainsider.de/sebastiaan-bornauw_18822/","kickbaseId":"2725"},{"lastName":"Denis Zakaria","delta":332330,"detailPageLink":"https://www.ligainsider.de/denis-zakaria_7664/","kickbaseId":"2063"},{"lastName":"Hannes Wolf","delta":320640,"detailPageLink":"https://www.ligainsider.de/hannes-wolf_12993/","kickbaseId":"2655"},{"lastName":"Herbert Bockhorn","delta":318412,"detailPageLink":"https://www.ligainsider.de/herbert-bockhorn_14547/","kickbaseId":"2292"},{"lastName":"André Hahn","delta":317122,"detailPageLink":"https://www.ligainsider.de/andre-hahn_2493/","kickbaseId":"570"},{"lastName":"Luca Netz","delta":310974,"detailPageLink":"https://www.ligainsider.de/luca-netz_24118/","kickbaseId":"2799"},{"lastName":"Yannick Gerhardt","delta":310306,"detailPageLink":"https://www.ligainsider.de/yannick-gerhardt_3942/","kickbaseId":"1298"},{"lastName":"Alessandro Schöpf","delta":305982,"detailPageLink":"https://www.ligainsider.de/alessandro-schoepf_2730/","kickbaseId":"1230"},{"lastName":"Luca Waldschmidt","delta":304982,"detailPageLink":"https://www.ligainsider.de/luca-waldschmidt_2594/","kickbaseId":"737"},{"lastName":"Marcus Ingvartsen","delta":301052,"detailPageLink":"https://www.ligainsider.de/marcus-ingvartsen_12598/","kickbaseId":"2642"},{"lastName":"Benno Schmitz","delta":301012,"detailPageLink":"https://www.ligainsider.de/benno-schmitz_2731/","kickbaseId":"1229"},{"lastName":"Raphael Framberger","delta":300132,"detailPageLink":"https://www.ligainsider.de/raphael-framberger_2470/","kickbaseId":"668"},{"lastName":"Manu Koné","delta":299061,"detailPageLink":"https://www.ligainsider.de/emmanuel-kouadio-kone_25803/","kickbaseId":"3011"},{"lastName":"Iago","delta":297632,"detailPageLink":"https://www.ligainsider.de/iago-amaral-borduchi_20626/","kickbaseId":"2662"},{"lastName":"Marin Pongračić","delta":293913,"detailPageLink":"https://www.ligainsider.de/marin-pongracic_13854/","kickbaseId":"2771"},{"lastName":"Marco Meyerhöfer","delta":290964,"detailPageLink":"https://www.ligainsider.de/marco-meyerhoefer_7637/","kickbaseId":"2985"},{"lastName":"Frederik Winther","delta":286149,"detailPageLink":"https://www.ligainsider.de/frederik-winther_24988/","kickbaseId":"3025"},{"lastName":"Daniel Caligiuri","delta":284881,"detailPageLink":"https://www.ligainsider.de/daniel-caligiuri_274/","kickbaseId":"542"},{"lastName":"Rani Khedira","delta":284773,"detailPageLink":"https://www.ligainsider.de/rani-khedira_2122/","kickbaseId":"51"},{"lastName":"Konstantinos Stafylidis","delta":283931,"detailPageLink":"https://www.ligainsider.de/konstantinos-stafylidis_2280/","kickbaseId":"616"},{"lastName":"Jean-Paul Boëtius","delta":281859,"detailPageLink":"https://www.ligainsider.de/jean-paul-boetius_12328/","kickbaseId":"2339"},{"lastName":"Niklas Stark","delta":278965,"detailPageLink":"https://www.ligainsider.de/niklas-stark_2441/","kickbaseId":"157"},{"lastName":"Dennis Jastrzembski","delta":277811,"detailPageLink":"https://www.ligainsider.de/dennis-jastrzembski_10662/","kickbaseId":"2265"},{"lastName":"Jeremiah St. Juste","delta":276580,"detailPageLink":"https://www.ligainsider.de/jeremiah-st-juste_16064/","kickbaseId":"2728"},{"lastName":"Karim Bellarabi","delta":275423,"detailPageLink":"https://www.ligainsider.de/karim-bellarabi_676/","kickbaseId":"486"},{"lastName":"Marco Richter","delta":274486,"detailPageLink":"https://www.ligainsider.de/marco-richter_12774/","kickbaseId":"2092"},{"lastName":"Ruben Vargas","delta":272811,"detailPageLink":"https://www.ligainsider.de/ruben-vargas_20532/","kickbaseId":"2664"},{"lastName":"Chris Richards","delta":268894,"detailPageLink":"https://www.ligainsider.de/chris-richards_20104/","kickbaseId":"2298"},{"lastName":"Julian Brandt","delta":261890,"detailPageLink":"https://www.ligainsider.de/julian-brandt_2467/","kickbaseId":"1192"},{"lastName":"Kevin-Prince Boateng","delta":257557,"detailPageLink":"https://www.ligainsider.de/kevin-prince-boateng_2352/","kickbaseId":"749"},{"lastName":"Salih Özcan","delta":257483,"detailPageLink":"https://www.ligainsider.de/salih-oezcan_6816/","kickbaseId":"1918"},{"lastName":"Sebastian Andersson","delta":256627,"detailPageLink":"https://www.ligainsider.de/sebastian-andersson_15907/","kickbaseId":"2394"},{"lastName":"Florian Krüger","delta":253188,"detailPageLink":"https://www.ligainsider.de/florian-krueger_18574/","kickbaseId":"2581"},{"lastName":"Masaya Okugawa","delta":250305,"detailPageLink":"https://www.ligainsider.de/masaya-okugawa_6469/","kickbaseId":"2494"},{"lastName":"Aster Vranckx","delta":241674,"detailPageLink":"https://www.ligainsider.de/aster-vranckx_25757/","kickbaseId":"3004"},{"lastName":"Jamal Musiala","delta":241377,"detailPageLink":"https://www.ligainsider.de/jamal-musiala_24149/","kickbaseId":"2804"},{"lastName":"Maximilian Mittelstädt","delta":232544,"detailPageLink":"https://www.ligainsider.de/maximilian-mittelstaedt_6206/","kickbaseId":"1664"},{"lastName":"László Bénes","delta":231099,"detailPageLink":"https://www.ligainsider.de/laszlo-benes_9586/","kickbaseId":"1877"},{"lastName":"Deyovaisio Zeefuik","delta":227428,"detailPageLink":"https://www.ligainsider.de/deyovaisio-zeefuik_24123/","kickbaseId":"2867"},{"lastName":"Noah Weißhaupt","delta":227111,"detailPageLink":"https://www.ligainsider.de/noah-weisshaupt_23598/","kickbaseId":"3017"},{"lastName":"Ádám Szalai","delta":226212,"detailPageLink":"https://www.ligainsider.de/adam-szalai_403/","kickbaseId":"463"},{"lastName":"Lars Stindl","delta":226010,"detailPageLink":"https://www.ligainsider.de/lars-stindl_487/","kickbaseId":"393"},{"lastName":"Alexander Schwolow","delta":224319,"detailPageLink":"https://www.ligainsider.de/alexander-schwolow_1781/","kickbaseId":"620"},{"lastName":"Ansgar  Knauff","delta":221500,"detailPageLink":"https://www.ligainsider.de/ansgar-knauff_24398/","kickbaseId":"2863"},{"lastName":"Anthony Modeste","delta":221236,"detailPageLink":"https://www.ligainsider.de/anthony-modeste_1223/","kickbaseId":"684"},{"lastName":"Angeliño","delta":221197,"detailPageLink":"https://www.ligainsider.de/angelino_7472/","kickbaseId":"2779"},{"lastName":"Cédric Brunner","delta":219009,"detailPageLink":"https://www.ligainsider.de/cedric-brunner_11557/","kickbaseId":"2429"},{"lastName":"Florian Niederlechner","delta":212774,"detailPageLink":"https://www.ligainsider.de/florian-niederlechner_5778/","kickbaseId":"1680"},{"lastName":"Lukas Nmecha","delta":211726,"detailPageLink":"https://www.ligainsider.de/lukas-nmecha_18385/","kickbaseId":"2724"},{"lastName":"Nico Schlotterbeck","delta":209570,"detailPageLink":"https://www.ligainsider.de/nico-schlotterbeck_20052/","kickbaseId":"2383"},{"lastName":"E. Choupo-Moting","delta":208316,"detailPageLink":"https://www.ligainsider.de/eric-maxim-choupo-moting_430/","kickbaseId":"336"},{"lastName":"Lucas Hernández","delta":207244,"detailPageLink":"https://www.ligainsider.de/lucas-hernandez_12218/","kickbaseId":"2647"},{"lastName":"Andreas Luthe","delta":203027,"detailPageLink":"https://www.ligainsider.de/andreas-luthe_172/","kickbaseId":"1116"},{"lastName":"Leroy Sané","delta":198590,"detailPageLink":"https://www.ligainsider.de/leroy-sane_3798/","kickbaseId":"1222"},{"lastName":"Orel Mangala","delta":197216,"detailPageLink":"https://www.ligainsider.de/orel-mangala_7078/","kickbaseId":"2049"},{"lastName":"Florian Wirtz","delta":195618,"detailPageLink":"https://www.ligainsider.de/florian-wirtz_23890/","kickbaseId":"2795"},{"lastName":"Benjamin Pavard","delta":195126,"detailPageLink":"https://www.ligainsider.de/benjamin-pavard_11327/","kickbaseId":"2054"},{"lastName":"Paulinho","delta":195058,"detailPageLink":"https://www.ligainsider.de/paulinho_19078/","kickbaseId":"2291"},{"lastName":"Robert Tesche","delta":194826,"detailPageLink":"https://www.ligainsider.de/robert-tesche_560/","kickbaseId":"325"},{"lastName":"Admir Mehmedi","delta":189997,"detailPageLink":"https://www.ligainsider.de/admir-mehmedi_1714/","kickbaseId":"703"},{"lastName":"Joe Scally","delta":188002,"detailPageLink":"https://www.ligainsider.de/joe-scally_23700/","kickbaseId":"2941"},{"lastName":"Jordan Beyer","delta":187244,"detailPageLink":"https://www.ligainsider.de/louis-jordan-beyer_14448/","kickbaseId":"2193"},{"lastName":"Nils Petersen","delta":186240,"detailPageLink":"https://www.ligainsider.de/nils-petersen_654/","kickbaseId":"317"},{"lastName":"Nordi Mukiele","delta":182505,"detailPageLink":"https://www.ligainsider.de/nordi-mukiele_18662/","kickbaseId":"2241"},{"lastName":"Djibril Sow","delta":180848,"detailPageLink":"https://www.ligainsider.de/djibril-sow_6510/","kickbaseId":"1738"},{"lastName":"Joakim Nilsson","delta":178924,"detailPageLink":"https://www.ligainsider.de/joakim-nilsson_20934/","kickbaseId":"2812"},{"lastName":"Ömer Faruk Beyaz","delta":178277,"detailPageLink":"https://www.ligainsider.de/oemer-faruk-beyaz_25661/","kickbaseId":"3000"},{"lastName":"Matthias Ginter","delta":175598,"detailPageLink":"https://www.ligainsider.de/matthias-ginter_1835/","kickbaseId":"49"},{"lastName":"Leandro Barreiro","delta":175429,"detailPageLink":"https://www.ligainsider.de/leandro-barreiro-martins_19288/","kickbaseId":"2335"},{"lastName":"Karim Onisiwo","delta":175168,"detailPageLink":"https://www.ligainsider.de/karim-onisiwo_7011/","kickbaseId":"1804"},{"lastName":"Levin Öztunali","delta":173927,"detailPageLink":"https://www.ligainsider.de/levin-oeztunali_2466/","kickbaseId":"672"},{"lastName":"Jérôme Roussillon","delta":171820,"detailPageLink":"https://www.ligainsider.de/jerome-roussillon_14541/","kickbaseId":"2321"},{"lastName":"Erik Durm","delta":170187,"detailPageLink":"https://www.ligainsider.de/erik-durm_1847/","kickbaseId":"732"},{"lastName":"Jetro Willems","delta":169964,"detailPageLink":"https://www.ligainsider.de/jetro-willems_6854/","kickbaseId":"2121"},{"lastName":"Kevin Behrens","delta":168977,"detailPageLink":"https://www.ligainsider.de/kevin-behrens_14742/","kickbaseId":"2496"},{"lastName":"Tim Lemperle","delta":168256,"detailPageLink":"https://www.ligainsider.de/tim-lemperle_23854/","kickbaseId":"2803"},{"lastName":"Christoph Baumgartner","delta":165816,"detailPageLink":"https://www.ligainsider.de/christoph-baumgartner_18640/","kickbaseId":"2275"},{"lastName":"Reece Oxford","delta":165813,"detailPageLink":"https://www.ligainsider.de/reece-oxford_9583/","kickbaseId":"2047"},{"lastName":"Simon Zoller","delta":161695,"detailPageLink":"https://www.ligainsider.de/simon-zoller_2648/","kickbaseId":"1534"},{"lastName":"Thomas Meunier","delta":156475,"detailPageLink":"https://www.ligainsider.de/thomas-meunier_3667/","kickbaseId":"2835"},{"lastName":"Taiwo Awoniyi","delta":156142,"detailPageLink":"https://www.ligainsider.de/taiwo-awoniyi_6805/","kickbaseId":"2729"},{"lastName":"Filip Kostić","delta":153426,"detailPageLink":"https://www.ligainsider.de/filip-kostic_5808/","kickbaseId":"1620"},{"lastName":"Kevin Möhwald","delta":153231,"detailPageLink":"https://www.ligainsider.de/kevin-moehwald_6096/","kickbaseId":"1841"},{"lastName":"Niko Gießelmann","delta":152349,"detailPageLink":"https://www.ligainsider.de/niko-giesselmann_2232/","kickbaseId":"102"},{"lastName":"Donyell Malen","delta":151765,"detailPageLink":"https://www.ligainsider.de/donyell-malen_22986/","kickbaseId":"3087"},{"lastName":"Rafał Gikiewicz","delta":150451,"detailPageLink":"https://www.ligainsider.de/rafal-gikiewicz_4199/","kickbaseId":"1936"},{"lastName":"Kerem Demirbay","delta":147638,"detailPageLink":"https://www.ligainsider.de/kerem-demirbay_2486/","kickbaseId":"81"},{"lastName":"Roland Sallai","delta":147446,"detailPageLink":"https://www.ligainsider.de/roland-sallai_8054/","kickbaseId":"2343"},{"lastName":"Danilo Soares","delta":145012,"detailPageLink":"https://www.ligainsider.de/danilo-soares_5734/","kickbaseId":"1544"},{"lastName":"Robert Andrich","delta":140389,"detailPageLink":"https://www.ligainsider.de/robert-andrich_2590/","kickbaseId":"663"},{"lastName":"Dominik Szoboszlai","delta":139508,"detailPageLink":"https://www.ligainsider.de/dominik-szoboszlai_18934/","kickbaseId":"2940"},{"lastName":"Patrik Schick","delta":137568,"detailPageLink":"https://www.ligainsider.de/patrik-schick_7794/","kickbaseId":"2746"},{"lastName":"Dennis Geiger","delta":135653,"detailPageLink":"https://www.ligainsider.de/dennis-geiger_10434/","kickbaseId":"1990"},{"lastName":"Breel Embolo","delta":132330,"detailPageLink":"https://www.ligainsider.de/breel-embolo_6091/","kickbaseId":"1869"},{"lastName":"Philipp Lienhart","delta":131061,"detailPageLink":"https://www.ligainsider.de/philipp-lienhart_13911/","kickbaseId":"2084"},{"lastName":"Alphonso Davies","delta":130470,"detailPageLink":"https://www.ligainsider.de/alphonso-davies_20098/","kickbaseId":"2366"},{"lastName":"Sebastian Vasiliadis","delta":125582,"detailPageLink":"https://www.ligainsider.de/sebastian-vasiliadis_19076/","kickbaseId":"2502"},{"lastName":"Daichi Kamada","delta":124912,"detailPageLink":"https://www.ligainsider.de/daichi-kamada_14160/","kickbaseId":"2059"},{"lastName":"Koen Casteels","delta":120247,"detailPageLink":"https://www.ligainsider.de/koen-casteels_1605/","kickbaseId":"497"},{"lastName":"Jonas Hector","delta":118528,"detailPageLink":"https://www.ligainsider.de/jonas-hector_1936/","kickbaseId":"1256"},{"lastName":"Konstantinos Mavropanos","delta":118072,"detailPageLink":"https://www.ligainsider.de/konstantinos-mavropanos_18854/","kickbaseId":"2838"},{"lastName":"Ihlas Bebou","delta":117767,"detailPageLink":"https://www.ligainsider.de/ihlas-bebou_4544/","kickbaseId":"1308"},{"lastName":"Yann Sommer","delta":116355,"detailPageLink":"https://www.ligainsider.de/yann-sommer_2577/","kickbaseId":"1568"},{"lastName":"Nico Elvedi","delta":115028,"detailPageLink":"https://www.ligainsider.de/nico-elvedi_6475/","kickbaseId":"1686"},{"lastName":"Florian Neuhaus","delta":114657,"detailPageLink":"https://www.ligainsider.de/florian-neuhaus_10416/","kickbaseId":"2261"},{"lastName":"Marvin Plattenhardt","delta":114201,"detailPageLink":"https://www.ligainsider.de/marvin-plattenhardt_581/","kickbaseId":"600"},{"lastName":"Myziane Maolida","delta":113474,"detailPageLink":"https://www.ligainsider.de/myziane-maolida_17104/","kickbaseId":"3145"},{"lastName":"Christopher Trimmel","delta":113196,"detailPageLink":"https://www.ligainsider.de/christopher-trimmel_5713/","kickbaseId":"2400"},{"lastName":"Maxence Lacroix","delta":112697,"detailPageLink":"https://www.ligainsider.de/maxence-lacroix_24609/","kickbaseId":"2878"},{"lastName":"Alassane Pléa","delta":112172,"detailPageLink":"https://www.ligainsider.de/alassane-plea_11770/","kickbaseId":"2288"},{"lastName":"Pavel Kaderábek","delta":110889,"detailPageLink":"https://www.ligainsider.de/pavel-kaderabek_6340/","kickbaseId":"1726"},{"lastName":"Mark Uth","delta":108406,"detailPageLink":"https://www.ligainsider.de/mark-uth_469/","kickbaseId":"1725"},{"lastName":"Christian Günter","delta":107917,"detailPageLink":"https://www.ligainsider.de/christian-guenter_2153/","kickbaseId":"89"},{"lastName":"Marvin Friedrich","delta":107801,"detailPageLink":"https://www.ligainsider.de/marvin-friedrich_3296/","kickbaseId":"1223"},{"lastName":"Moussa Diaby","delta":106675,"detailPageLink":"https://www.ligainsider.de/moussa-diaby_20616/","kickbaseId":"2661"},{"lastName":"Martin Hinteregger","delta":106099,"detailPageLink":"https://www.ligainsider.de/martin-hinteregger_1293/","kickbaseId":"1810"},{"lastName":"Jude Bellingham","delta":105218,"detailPageLink":"https://www.ligainsider.de/jude-bellingham_24076/","kickbaseId":"2845"},{"lastName":"Kingsley Coman","delta":102800,"detailPageLink":"https://www.ligainsider.de/kingsley-coman_6690/","kickbaseId":"1774"},{"lastName":"Julian Ryerson","delta":101560,"detailPageLink":"https://www.ligainsider.de/julian-ryerson_18478/","kickbaseId":"2395"},{"lastName":"Woo-yeong Jeong","delta":101152,"detailPageLink":"https://www.ligainsider.de/woo-yeong-jeong_14145/","kickbaseId":"2302"},{"lastName":"Manuel Neuer","delta":101096,"detailPageLink":"https://www.ligainsider.de/manuel-neuer_114/","kickbaseId":"237"},{"lastName":"Cedric Teuchert","delta":99760,"detailPageLink":"https://www.ligainsider.de/cedric-teuchert_6095/","kickbaseId":"1842"},{"lastName":"Lucas Höler","delta":98905,"detailPageLink":"https://www.ligainsider.de/lucas-hoeler_6593/","kickbaseId":"2176"},{"lastName":"Jonathan Tah","delta":95809,"detailPageLink":"https://www.ligainsider.de/jonathan-tah_2385/","kickbaseId":"173"},{"lastName":"Florian Grillitsch","delta":95059,"detailPageLink":"https://www.ligainsider.de/florian-grillitsch_5385/","kickbaseId":"1703"},{"lastName":"Mohamed Simakan","delta":93347,"detailPageLink":"https://www.ligainsider.de/mohamed-simakan_24093/","kickbaseId":"3001"},{"lastName":"Evan N'Dicka","delta":92061,"detailPageLink":"https://www.ligainsider.de/obite-evan-n-dicka_20006/","kickbaseId":"2282"},{"lastName":"Raphaël Guerreiro","delta":89856,"detailPageLink":"https://www.ligainsider.de/raphael-guerreiro_6795/","kickbaseId":"1862"},{"lastName":"Manuel Akanji","delta":89511,"detailPageLink":"https://www.ligainsider.de/manuel-akanji_12321/","kickbaseId":"2181"},{"lastName":"Jan Thielmann","delta":88168,"detailPageLink":"https://www.ligainsider.de/jan-thielmann_21998/","kickbaseId":"2765"},{"lastName":"Lukas Kübler","delta":86118,"detailPageLink":"https://www.ligainsider.de/lukas-kuebler_1935/","kickbaseId":"1257"},{"lastName":"Kingsley Ehizibue","delta":85104,"detailPageLink":"https://www.ligainsider.de/kingsley-ehizibue_20599/","kickbaseId":"2648"},{"lastName":"Jeremie Frimpong","delta":84802,"detailPageLink":"https://www.ligainsider.de/jeremie-frimpong_22308/","kickbaseId":"2948"},{"lastName":"Sven Ulreich","delta":79948,"detailPageLink":"https://www.ligainsider.de/sven-ulreich_205/","kickbaseId":"383"},{"lastName":"Elvis Rexhbeçaj","delta":79330,"detailPageLink":"https://www.ligainsider.de/elvis-rexhbecaj_13707/","kickbaseId":"2091"},{"lastName":"Wout Weghorst","delta":78982,"detailPageLink":"https://www.ligainsider.de/wout-weghorst_11463/","kickbaseId":"2229"},{"lastName":"Timo Baumgartl","delta":76853,"detailPageLink":"https://www.ligainsider.de/timo-baumgartl_3284/","kickbaseId":"1584"},{"lastName":"Dayot Upamecano","delta":76354,"detailPageLink":"https://www.ligainsider.de/dayot-upamecano_11541/","kickbaseId":"1991"},{"lastName":"Dani Olmo","delta":76040,"detailPageLink":"https://www.ligainsider.de/dani-olmo_12291/","kickbaseId":"2776"},{"lastName":"Florian Müller","delta":75161,"detailPageLink":"https://www.ligainsider.de/florian-mueller_7609/","kickbaseId":"1910"},{"lastName":"Gregor Kobel","delta":73911,"detailPageLink":"https://www.ligainsider.de/gregor-kobel_9357/","kickbaseId":"1873"},{"lastName":"Mats Hummels","delta":73615,"detailPageLink":"https://www.ligainsider.de/mats-hummels_131/","kickbaseId":"304"},{"lastName":"Stefan Bell","delta":72858,"detailPageLink":"https://www.ligainsider.de/stefan-bell_521/","kickbaseId":"550"},{"lastName":"Willi Orbán","delta":71883,"detailPageLink":"https://www.ligainsider.de/willi-orban_1667/","kickbaseId":"1246"},{"lastName":"Leon Goretzka","delta":65162,"detailPageLink":"https://www.ligainsider.de/leon-goretzka_1863/","kickbaseId":"660"},{"lastName":"Marius Wolf","delta":63749,"detailPageLink":"https://www.ligainsider.de/marius-wolf_5670/","kickbaseId":"1809"},{"lastName":"Ellyes Skhiri","delta":63661,"detailPageLink":"https://www.ligainsider.de/ellyes-skhiri_20776/","kickbaseId":"2718"},{"lastName":"Charles Aránguiz","delta":63484,"detailPageLink":"https://www.ligainsider.de/charles-aranguiz_5279/","kickbaseId":"1766"},{"lastName":"Dodi Lukébakio","delta":59163,"detailPageLink":"https://www.ligainsider.de/dodi-lukebakio_11859/","kickbaseId":"2308"},{"lastName":"Almamy Touré","delta":58048,"detailPageLink":"https://www.ligainsider.de/almamy-toure_12425/","kickbaseId":"2376"},{"lastName":"Armel Bella-Kotchap","delta":56983,"detailPageLink":"https://www.ligainsider.de/armel-bella-kotchap_20048/","kickbaseId":"2590"},{"lastName":"Thomas Müller","delta":56886,"detailPageLink":"https://www.ligainsider.de/thomas-mueller_249/","kickbaseId":"450"},{"lastName":"Márton Dárdai","delta":54126,"detailPageLink":"https://www.ligainsider.de/marton-dardai_24119/","kickbaseId":"2796"},{"lastName":"Amos Pieper","delta":53021,"detailPageLink":"https://www.ligainsider.de/amos-pieper_7061/","kickbaseId":"2294"},{"lastName":"Odilon Kossounou","delta":52849,"detailPageLink":"https://www.ligainsider.de/odilon-kossounou_22070/","kickbaseId":"3079"},{"lastName":"Oliver Baumann","delta":51478,"detailPageLink":"https://www.ligainsider.de/oliver-baumann_567/","kickbaseId":"524"},{"lastName":"Tanguy Nianzou","delta":49936,"detailPageLink":"https://www.ligainsider.de/tanguy-nianzou-kouassi_23744/","kickbaseId":"2823"},{"lastName":"Robin Zentner","delta":49739,"detailPageLink":"https://www.ligainsider.de/robin-zentner_3298/","kickbaseId":"1590"},{"lastName":"Jonathan Schmid","delta":49687,"detailPageLink":"https://www.ligainsider.de/jonathan-schmid_641/","kickbaseId":"605"},{"lastName":"Christopher Nkunku","delta":48602,"detailPageLink":"https://www.ligainsider.de/christopher-nkunku_12446/","kickbaseId":"2687"},{"lastName":"Ridle Baku","delta":48312,"detailPageLink":"https://www.ligainsider.de/ridle-baku_15835/","kickbaseId":"2141"},{"lastName":"Robin Hack","delta":47555,"detailPageLink":"https://www.ligainsider.de/robin-hack_14139/","kickbaseId":"2074"},{"lastName":"Maximilian Bauer","delta":47043,"detailPageLink":"https://www.ligainsider.de/maximilian-bauer_14214/","kickbaseId":"2582"},{"lastName":"Maximilian Arnold","delta":46324,"detailPageLink":"https://www.ligainsider.de/maximilian-arnold_1673/","kickbaseId":"44"},{"lastName":"Alexander Hack","delta":44598,"detailPageLink":"https://www.ligainsider.de/alexander-hack_5877/","kickbaseId":"1789"},{"lastName":"Hamadi Al Ghaddioui","delta":44165,"detailPageLink":"https://www.ligainsider.de/hamadi-al-ghaddioui_10736/","kickbaseId":"2541"},{"lastName":"Max Kruse","delta":43046,"detailPageLink":"https://www.ligainsider.de/max-kruse_482/","kickbaseId":"369"},{"lastName":"Marco Reus","delta":42872,"detailPageLink":"https://www.ligainsider.de/marco-reus_332/","kickbaseId":"399"},{"lastName":"Serge Gnabry","delta":42310,"detailPageLink":"https://www.ligainsider.de/serge-gnabry_4815/","kickbaseId":"1961"},{"lastName":"Ajdin Hrustić","delta":40372,"detailPageLink":"https://www.ligainsider.de/ajdin-hrustic_24639/","kickbaseId":"2908"},{"lastName":"Silvan Widmer","delta":37052,"detailPageLink":"https://www.ligainsider.de/silvan-widmer_1938/","kickbaseId":"3041"},{"lastName":"Robert Lewandowski","delta":36002,"detailPageLink":"https://www.ligainsider.de/robert-lewandowski_366/","kickbaseId":"455"},{"lastName":"Marcel Sabitzer","delta":34929,"detailPageLink":"https://www.ligainsider.de/marcel-sabitzer_2020/","kickbaseId":"1856"},{"lastName":"Erling Braut Haaland","delta":34749,"detailPageLink":"https://www.ligainsider.de/erling-braut-haaland_20212/","kickbaseId":"2767"},{"lastName":"Timo Hübers","delta":34611,"detailPageLink":"https://www.ligainsider.de/timo-huebers_8912/","kickbaseId":"2069"},{"lastName":"Manuel Prietl","delta":33160,"detailPageLink":"https://www.ligainsider.de/manuel-prietl_9584/","kickbaseId":"2416"},{"lastName":"Sam Lammers","delta":31844,"detailPageLink":"https://www.ligainsider.de/sam-lammers_13251/","kickbaseId":"3144"},{"lastName":"Kevin Akpoguma","delta":30585,"detailPageLink":"https://www.ligainsider.de/kevin-akpoguma_2477/","kickbaseId":"96"},{"lastName":"Edmond Tapsoba","delta":30523,"detailPageLink":"https://www.ligainsider.de/edmond-tapsoba_19022/","kickbaseId":"2783"},{"lastName":"Christopher Lenz","delta":26834,"detailPageLink":"https://www.ligainsider.de/christopher-lenz_2123/","kickbaseId":"1739"},{"lastName":"Lukáš Hrádecký","delta":21687,"detailPageLink":"https://www.ligainsider.de/lukas-hradecky_6694/","kickbaseId":"1761"},{"lastName":"Jens Petter Hauge","delta":19124,"detailPageLink":"https://www.ligainsider.de/jens-petter-hauge_25321/","kickbaseId":"3125"},{"lastName":"Jacob Bruun Larsen","delta":18572,"detailPageLink":"https://www.ligainsider.de/jacob-bruun-larsen_6837/","kickbaseId":"1781"},{"lastName":"Davie Selke","delta":15902,"detailPageLink":"https://www.ligainsider.de/davie-selke_2948/","kickbaseId":"1183"},{"lastName":"Robin Knoche","delta":13931,"detailPageLink":"https://www.ligainsider.de/robin-knoche_1629/","kickbaseId":"623"},{"lastName":"Joshua Kimmich","delta":12945,"detailPageLink":"https://www.ligainsider.de/joshua-kimmich_5768/","kickbaseId":"1685"},{"lastName":"Wataru Endo","delta":12651,"detailPageLink":"https://www.ligainsider.de/wataru-endo_23590/","kickbaseId":"2837"},{"lastName":"Stevan Jovetić","delta":12282,"detailPageLink":"https://www.ligainsider.de/stevan-jovetic_4756/","kickbaseId":"3088"},{"lastName":"Chris Führich","delta":9717,"detailPageLink":"https://www.ligainsider.de/chris-fuehrich_18542/","kickbaseId":"2172"},{"lastName":"Robert Gumny","delta":6523,"detailPageLink":"https://www.ligainsider.de/robert-gumny_18666/","kickbaseId":"2885"},{"lastName":"Mark Flekken","delta":6241,"detailPageLink":"https://www.ligainsider.de/mark-flekken_4530/","kickbaseId":"72"},{"lastName":"Nadiem Amiri","delta":4503,"detailPageLink":"https://www.ligainsider.de/nadiem-amiri_5815/","kickbaseId":"1639"},{"lastName":"Jonas Hofmann","delta":3376,"detailPageLink":"https://www.ligainsider.de/jonas-hofmann_2362/","kickbaseId":"78"},{"lastName":"Sebastian Griesbeck","delta":2745,"detailPageLink":"https://www.ligainsider.de/sebastian-griesbeck_5791/","kickbaseId":"2432"},{"lastName":"Axel Witsel","delta":2702,"detailPageLink":"https://www.ligainsider.de/axel-witsel_4551/","kickbaseId":"2323"},{"lastName":"Moussa Niakhaté","delta":-514209,"detailPageLink":"https://www.ligainsider.de/moussa-niakhate_19258/","kickbaseId":"2284"},{"lastName":"Ilaix Moriba","delta":-504902,"detailPageLink":"https://www.ligainsider.de/ilaix-moriba_25848/","kickbaseId":"3140"},{"lastName":"Joško Gvardiol","delta":-439312,"detailPageLink":"https://www.ligainsider.de/josko-gvardiol_23402/","kickbaseId":"3003"},{"lastName":"Emil Forsberg","delta":-413905,"detailPageLink":"https://www.ligainsider.de/emil-forsberg_6158/","kickbaseId":"1900"},{"lastName":"Ramy Bensebaini","delta":-410633,"detailPageLink":"https://www.ligainsider.de/ramy-bensebaini_7791/","kickbaseId":"2736"},{"lastName":"Waldemar Anton","delta":-398590,"detailPageLink":"https://www.ligainsider.de/waldemar-anton_5837/","kickbaseId":"1704"},{"lastName":"Renato Steffen","delta":-366775,"detailPageLink":"https://www.ligainsider.de/renato-steffen_7785/","kickbaseId":"2179"},{"lastName":"Giovanni Reyna","delta":-350840,"detailPageLink":"https://www.ligainsider.de/giovanni-reyna_20760/","kickbaseId":"2692"},{"lastName":"Manuel Riemann","delta":-294557,"detailPageLink":"https://www.ligainsider.de/manuel-riemann_5895/","kickbaseId":"1405"},{"lastName":"Rafael Santos Borré","delta":-289595,"detailPageLink":"https://www.ligainsider.de/rafael-santos-borre_12083/","kickbaseId":"3030"},{"lastName":"Jae-sung Lee","delta":-289273,"detailPageLink":"https://www.ligainsider.de/jae-sung-lee_21202/","kickbaseId":"2476"},{"lastName":"Borna Sosa","delta":-279610,"detailPageLink":"https://www.ligainsider.de/borna-sosa_12284/","kickbaseId":"2247"},{"lastName":"Sebastian Rudy","delta":-276009,"detailPageLink":"https://www.ligainsider.de/sebastian-rudy_188/","kickbaseId":"410"},{"lastName":"Fabian Klos","delta":-266195,"detailPageLink":"https://www.ligainsider.de/fabian-klos_1448/","kickbaseId":"1115"},{"lastName":"Tyler Adams","delta":-266048,"detailPageLink":"https://www.ligainsider.de/tyler-adams_14025/","kickbaseId":"2364"},{"lastName":"Stefan Posch","delta":-264165,"detailPageLink":"https://www.ligainsider.de/stefan-posch_12798/","kickbaseId":"2006"},{"lastName":"Ondrej Duda","delta":-253358,"detailPageLink":"https://www.ligainsider.de/ondrej-duda_6360/","kickbaseId":"1919"},{"lastName":"Saša Kalajdžić","delta":-237004,"detailPageLink":"https://www.ligainsider.de/sasa-kalajdzic_20605/","kickbaseId":"2819"},{"lastName":"Jesper Lindstrøm","delta":-235648,"detailPageLink":"https://www.ligainsider.de/jesper-lindstroem_26157/","kickbaseId":"3044"},{"lastName":"Florian Kainz","delta":-230969,"detailPageLink":"https://www.ligainsider.de/florian-kainz_6982/","kickbaseId":"1903"},{"lastName":"Paul Jaeckel","delta":-228696,"detailPageLink":"https://www.ligainsider.de/paul-jaeckel_13704/","kickbaseId":"2197"},{"lastName":"Stefan Ortega Moreno","delta":-226683,"detailPageLink":"https://www.ligainsider.de/stefan-ortega-moreno_1905/","kickbaseId":"1163"},{"lastName":"Sebastian Polter","delta":-216437,"detailPageLink":"https://www.ligainsider.de/sebastian-polter_625/","kickbaseId":"496"},{"lastName":"Philipp Förster","delta":-203329,"detailPageLink":"https://www.ligainsider.de/philipp-foerster_12975/","kickbaseId":"2526"},{"lastName":"Vasilios Lampropoulos","delta":-202847,"detailPageLink":"https://www.ligainsider.de/vasilios-lampropoulos_16396/","kickbaseId":"2997"},{"lastName":"Amadou Haidara","delta":-189403,"detailPageLink":"https://www.ligainsider.de/amadou-haidara_16768/","kickbaseId":"2365"},{"lastName":"Maximilian Eggestein","delta":-186628,"detailPageLink":"https://www.ligainsider.de/maximilian-eggestein_6131/","kickbaseId":"1645"},{"lastName":"Branimir Hrgota","delta":-186096,"detailPageLink":"https://www.ligainsider.de/branimir-hrgota_2169/","kickbaseId":"84"},{"lastName":"Sascha Burchert","delta":-178450,"detailPageLink":"https://www.ligainsider.de/sascha-burchert_299/","kickbaseId":"697"},{"lastName":"Stefan Lainer","delta":-174257,"detailPageLink":"https://www.ligainsider.de/stefan-lainer_11546/","kickbaseId":"2644"},{"lastName":"Roberto Massimo","delta":-173210,"detailPageLink":"https://www.ligainsider.de/roberto-massimo_18407/","kickbaseId":"2546"},{"lastName":"Niklas Süle","delta":-170425,"detailPageLink":"https://www.ligainsider.de/niklas-suele_2584/","kickbaseId":"163"},{"lastName":"Lucas Alario","delta":-166961,"detailPageLink":"https://www.ligainsider.de/lucas-alario_5947/","kickbaseId":"2157"},{"lastName":"Munas Dabbur","delta":-165581,"detailPageLink":"https://www.ligainsider.de/munas-dabbur_7624/","kickbaseId":"2768"},{"lastName":"Gerrit Holtmann","delta":-164706,"detailPageLink":"https://www.ligainsider.de/gerrit-holtmann_6352/","kickbaseId":"1881"},{"lastName":"Emre Can","delta":-162955,"detailPageLink":"https://www.ligainsider.de/emre-can_1812/","kickbaseId":"54"},{"lastName":"Marcus Thuram","delta":-157289,"detailPageLink":"https://www.ligainsider.de/marcus-thuram_20516/","kickbaseId":"2704"},{"lastName":"Andrej Kramarić","delta":-153795,"detailPageLink":"https://www.ligainsider.de/andrej-kramaric_2439/","kickbaseId":"1815"},{"lastName":"Angelo Stiller","delta":-152599,"detailPageLink":"https://www.ligainsider.de/angelo-stiller_20766/","kickbaseId":"2694"},{"lastName":"Lukas Klostermann","delta":-143988,"detailPageLink":"https://www.ligainsider.de/lukas-klostermann_5622/","kickbaseId":"1333"},{"lastName":"Vincenzo Grifo","delta":-142419,"detailPageLink":"https://www.ligainsider.de/vincenzo-grifo_2361/","kickbaseId":"118"},{"lastName":"Rafael Czichos","delta":-140403,"detailPageLink":"https://www.ligainsider.de/rafael-czichos_13983/","kickbaseId":"2209"},{"lastName":"Kevin Vogt","delta":-135541,"detailPageLink":"https://www.ligainsider.de/kevin-vogt_209/","kickbaseId":"477"},{"lastName":"Xaver Schlager","delta":-135378,"detailPageLink":"https://www.ligainsider.de/xaver-schlager_11547/","kickbaseId":"2649"},{"lastName":"Ishak Belfodil","delta":-130934,"detailPageLink":"https://www.ligainsider.de/ishak-belfodil_2429/","kickbaseId":"2153"},{"lastName":"Mateo Klimowicz","delta":-130895,"detailPageLink":"https://www.ligainsider.de/mateo-klimowicz_20541/","kickbaseId":"2818"},{"lastName":"Erhan Mašović","delta":-127535,"detailPageLink":"https://www.ligainsider.de/erhan-masovic_25008/","kickbaseId":"2994"},{"lastName":"Carlos Gruezo","delta":-127018,"detailPageLink":"https://www.ligainsider.de/carlos-gruezo_3312/","kickbaseId":"1212"},{"lastName":"Tony Jantschke","delta":-126438,"detailPageLink":"https://www.ligainsider.de/tony-jantschke_304/","kickbaseId":"387"},{"lastName":"Timothy Fosu-Mensah","delta":-125964,"detailPageLink":"https://www.ligainsider.de/timothy-fosu-mensah_7481/","kickbaseId":"2944"},{"lastName":"Péter Gulácsi","delta":-124786,"detailPageLink":"https://www.ligainsider.de/peter-gulacsi_6429/","kickbaseId":"1896"},{"lastName":"Gideon Jung","delta":-123047,"detailPageLink":"https://www.ligainsider.de/gideon-jung_5557/","kickbaseId":"1604"},{"lastName":"Lennart Czyborra","delta":-122664,"detailPageLink":"https://www.ligainsider.de/lennart-czyborra_18576/","kickbaseId":"3134"},{"lastName":"Wahid Faghir","delta":-122659,"detailPageLink":"https://www.ligainsider.de/wahid-faghir_26239/","kickbaseId":"3138"},{"lastName":"Daniel Ginczek","delta":-121977,"detailPageLink":"https://www.ligainsider.de/daniel-ginczek_485/","kickbaseId":"540"},{"lastName":"Adrian Fein","delta":-121952,"detailPageLink":"https://www.ligainsider.de/adrian-fein_10468/","kickbaseId":"2099"},{"lastName":"Fabio Blanco","delta":-119820,"detailPageLink":"https://www.ligainsider.de/fabio-blanco-gomez_26062/","kickbaseId":"3008"},{"lastName":"Max Christiansen","delta":-119158,"detailPageLink":"https://www.ligainsider.de/max-christiansen_4507/","kickbaseId":"1693"},{"lastName":"Kevin Mbabu","delta":-118468,"detailPageLink":"https://www.ligainsider.de/kevin-mbabu_6856/","kickbaseId":"2639"},{"lastName":"Benjamin Hübner","delta":-117304,"detailPageLink":"https://www.ligainsider.de/benjamin-huebner_5731/","kickbaseId":"1429"},{"lastName":"Daniel Brosinski","delta":-115617,"detailPageLink":"https://www.ligainsider.de/daniel-brosinski_955/","kickbaseId":"377"},{"lastName":"Jeremy Dudziak","delta":-115596,"detailPageLink":"https://www.ligainsider.de/jeremy-dudziak_5820/","kickbaseId":"1657"},{"lastName":"Sergio Córdova","delta":-115107,"detailPageLink":"https://www.ligainsider.de/sergio-cordova_14181/","kickbaseId":"2083"},{"lastName":"Andrés Andrade","delta":-113986,"detailPageLink":"https://www.ligainsider.de/andres-andrade_22772/","kickbaseId":"3142"},{"lastName":"Justin Hoogma","delta":-112498,"detailPageLink":"https://www.ligainsider.de/justin-hoogma_14106/","kickbaseId":"2066"},{"lastName":"Mitchel Bakker","delta":-109335,"detailPageLink":"https://www.ligainsider.de/mitchel-bakker_21916/","kickbaseId":"3046"},{"lastName":"Alfreð Finnbogason","delta":-109241,"detailPageLink":"https://www.ligainsider.de/alfred-finnbogason_2658/","kickbaseId":"1826"},{"lastName":"Marc Roca","delta":-109079,"detailPageLink":"https://www.ligainsider.de/marc-roca_20656/","kickbaseId":"2910"},{"lastName":"Ermin Bičakčić","delta":-107923,"detailPageLink":"https://www.ligainsider.de/ermin-bicakcic_663/","kickbaseId":"717"},{"lastName":"Nathan de Medina","delta":-106997,"detailPageLink":"https://www.ligainsider.de/nathan-de-medina_11850/","kickbaseId":"2849"},{"lastName":"Amin Younes","delta":-106001,"detailPageLink":"https://www.ligainsider.de/amin-younes_1836/","kickbaseId":"57"},{"lastName":"Julian Baumgartlinger","delta":-105786,"detailPageLink":"https://www.ligainsider.de/julian-baumgartlinger_1313/","kickbaseId":"374"},{"lastName":"Ragnar Ache","delta":-103945,"detailPageLink":"https://www.ligainsider.de/ragnar-ache_23720/","kickbaseId":"2855"},{"lastName":"Edimilson Fernandes","delta":-102481,"detailPageLink":"https://www.ligainsider.de/edimilson-fernandes_7666/","kickbaseId":"2643"},{"lastName":"Thorgan Hazard","delta":-102467,"detailPageLink":"https://www.ligainsider.de/thorgan-hazard_4196/","kickbaseId":"1583"},{"lastName":"Andi Zeqiri","delta":-102404,"detailPageLink":"https://www.ligainsider.de/andi-zeqiri_26572/","kickbaseId":"3137"},{"lastName":"Dominique Heintz","delta":-101575,"detailPageLink":"https://www.ligainsider.de/dominique-heintz_1669/","kickbaseId":"1249"},{"lastName":"Sebastian Rode","delta":-101281,"detailPageLink":"https://www.ligainsider.de/sebastian-rode_451/","kickbaseId":"392"},{"lastName":"Keven Schlotterbeck","delta":-100928,"detailPageLink":"https://www.ligainsider.de/keven-schlotterbeck_19286/","kickbaseId":"2274"},{"lastName":"Paul Nebel","delta":-99898,"detailPageLink":"https://www.ligainsider.de/paul-nebel_20674/","kickbaseId":"2895"},{"lastName":"Anthony Losilla","delta":-99487,"detailPageLink":"https://www.ligainsider.de/anthony-losilla_5649/","kickbaseId":"1514"},{"lastName":"Tuta","delta":-99432,"detailPageLink":"https://www.ligainsider.de/lucas-silva-melo_20444/","kickbaseId":"2378"},{"lastName":"Miloš Pantović","delta":-98035,"detailPageLink":"https://www.ligainsider.de/milos-pantovic_6885/","kickbaseId":"1794"},{"lastName":"Michael Gregoritsch","delta":-97299,"detailPageLink":"https://www.ligainsider.de/michael-gregoritsch_1512/","kickbaseId":"493"},{"lastName":"Tymoteusz Puchacz","delta":-96926,"detailPageLink":"https://www.ligainsider.de/tymoteusz-puchacz_24989/","kickbaseId":"3020"},{"lastName":"Dan-Axel Zagadou","delta":-96743,"detailPageLink":"https://www.ligainsider.de/dan-axel-zagadou_12683/","kickbaseId":"2068"},{"lastName":"Rick van Drongelen","delta":-95557,"detailPageLink":"https://www.ligainsider.de/rick-van-drongelen_14532/","kickbaseId":"2133"},{"lastName":"Georginio Rutter","delta":-94708,"detailPageLink":"https://www.ligainsider.de/georginio-rutter_25119/","kickbaseId":"2949"},{"lastName":"Benjamin Henrichs","delta":-94680,"detailPageLink":"https://www.ligainsider.de/benjamin-henrichs_5680/","kickbaseId":"1689"},{"lastName":"Keanan Bennetts","delta":-94251,"detailPageLink":"https://www.ligainsider.de/keanan-bennetts_19178/","kickbaseId":"2240"},{"lastName":"Fabian Kunze","delta":-92816,"detailPageLink":"https://www.ligainsider.de/fabian-kunze_19820/","kickbaseId":"2821"},{"lastName":"Philipp Klement","delta":-92657,"detailPageLink":"https://www.ligainsider.de/philipp-klement_1455/","kickbaseId":"6"},{"lastName":"Amine Adli","delta":-92411,"detailPageLink":"https://www.ligainsider.de/amine-adli_26134/","kickbaseId":"3132"},{"lastName":"Tomas Ostrak","delta":-91759,"detailPageLink":"https://www.ligainsider.de/tomas-ostrak_18674/","kickbaseId":"3028"},{"lastName":"Jordan Torunarigha","delta":-90927,"detailPageLink":"https://www.ligainsider.de/jordan-torunarigha_6513/","kickbaseId":"1978"},{"lastName":"Aymen Barkok","delta":-90904,"detailPageLink":"https://www.ligainsider.de/aymen-barkok_12576/","kickbaseId":"1971"},{"lastName":"Marcel Halstenberg","delta":-90772,"detailPageLink":"https://www.ligainsider.de/marcel-halstenberg_2436/","kickbaseId":"77"},{"lastName":"Kevin Schade","delta":-89854,"detailPageLink":"https://www.ligainsider.de/kevin-schade_24157/","kickbaseId":"2930"},{"lastName":"Luca Kilian","delta":-89466,"detailPageLink":"https://www.ligainsider.de/luca-kilian_20577/","kickbaseId":"2349"},{"lastName":"Dejan Ljubicic","delta":-89298,"detailPageLink":"https://www.ligainsider.de/dejan-ljubicic_24396/","kickbaseId":"3029"},{"lastName":"Kevin Stöger","delta":-89048,"detailPageLink":"https://www.ligainsider.de/kevin-stoeger_692/","kickbaseId":"619"},{"lastName":"Robert Skov","delta":-87991,"detailPageLink":"https://www.ligainsider.de/robert-skov_18702/","kickbaseId":"2717"},{"lastName":"Fredrik Jensen","delta":-87649,"detailPageLink":"https://www.ligainsider.de/fredrik-jensen_19218/","kickbaseId":"2263"},{"lastName":"Jurgen Ekkelenkamp","delta":-86975,"detailPageLink":"https://www.ligainsider.de/jurgen-ekkelenkamp_22044/","kickbaseId":"3135"},{"lastName":"Youssoufa Moukoko","delta":-86765,"detailPageLink":"https://www.ligainsider.de/youssoufa-moukoko_24068/","kickbaseId":"2866"},{"lastName":"Felix Nmecha","delta":-85737,"detailPageLink":"https://www.ligainsider.de/felix-nmecha_25090/","kickbaseId":"3069"},{"lastName":"Bryan Lasme","delta":-85726,"detailPageLink":"https://www.ligainsider.de/bryan-lasme_26131/","kickbaseId":"3022"},{"lastName":"Janni Serra","delta":-85555,"detailPageLink":"https://www.ligainsider.de/janni-serra_6836/","kickbaseId":"2474"},{"lastName":"Timo Horn","delta":-84522,"detailPageLink":"https://www.ligainsider.de/timo-horn_516/","kickbaseId":"1245"},{"lastName":"Brian Brobbey","delta":-83748,"detailPageLink":"https://www.ligainsider.de/brian-brobbey_25589/","kickbaseId":"3002"},{"lastName":"Paulo Otávio","delta":-83460,"detailPageLink":"https://www.ligainsider.de/paulo-otavio_12680/","kickbaseId":"2447"},{"lastName":"Louis Schaub","delta":-81854,"detailPageLink":"https://www.ligainsider.de/louis-schaub_6758/","kickbaseId":"2409"},{"lastName":"Makoto Hasebe","delta":-80946,"detailPageLink":"https://www.ligainsider.de/makoto-hasebe_342/","kickbaseId":"285"},{"lastName":"Dickson Abiama","delta":-80068,"detailPageLink":"https://www.ligainsider.de/dickson-abiama_24858/","kickbaseId":"2982"},{"lastName":"Gian-Luca Itter","delta":-78647,"detailPageLink":"https://www.ligainsider.de/gian-luca-itter_12687/","kickbaseId":"2009"},{"lastName":"Corentin Tolisso","delta":-78274,"detailPageLink":"https://www.ligainsider.de/corentin-tolisso_12408/","kickbaseId":"2046"},{"lastName":"Maxim Leitsch","delta":-77300,"detailPageLink":"https://www.ligainsider.de/maxim-leitsch_10606/","kickbaseId":"2515"},{"lastName":"Christopher Antwi-Adjei","delta":-76559,"detailPageLink":"https://www.ligainsider.de/christopher-antwi-adjei_15297/","kickbaseId":"2539"},{"lastName":"Sheraldo Becker","delta":-75897,"detailPageLink":"https://www.ligainsider.de/sheraldo-becker_20640/","kickbaseId":"2646"},{"lastName":"Danny da Costa","delta":-75869,"detailPageLink":"https://www.ligainsider.de/danny-da-costa_650/","kickbaseId":"1540"},{"lastName":"Erik Thommy","delta":-75441,"detailPageLink":"https://www.ligainsider.de/erik-thommy_3307/","kickbaseId":"1208"},{"lastName":"Tanguy Coulibaly","delta":-75298,"detailPageLink":"https://www.ligainsider.de/tanguy-coulibaly_21572/","kickbaseId":"2824"},{"lastName":"Hiroki Ito","delta":-74205,"detailPageLink":"https://www.ligainsider.de/hiroki-ito_26128/","kickbaseId":"3089"},{"lastName":"Cedric Itten","delta":-73845,"detailPageLink":"https://www.ligainsider.de/cedric-itten_18071/","kickbaseId":"3139"},{"lastName":"Niklas Tauer","delta":-72750,"detailPageLink":"https://www.ligainsider.de/niklas-tauer_20680/","kickbaseId":"2891"},{"lastName":"Diadié Samassékou","delta":-72660,"detailPageLink":"https://www.ligainsider.de/diadie-samassekou_11545/","kickbaseId":"2737"},{"lastName":"Nico Schulz","delta":-72522,"detailPageLink":"https://www.ligainsider.de/nico-schulz_675/","kickbaseId":"726"},{"lastName":"Christoph Kramer","delta":-72292,"detailPageLink":"https://www.ligainsider.de/christoph-kramer_1465/","kickbaseId":"8"},{"lastName":"Daniel Didavi","delta":-72116,"detailPageLink":"https://www.ligainsider.de/daniel-didavi_180/","kickbaseId":"469"},{"lastName":"Yussuf Poulsen","delta":-70981,"detailPageLink":"https://www.ligainsider.de/yussuf-poulsen_5765/","kickbaseId":"1865"},{"lastName":"Jamie Leweling","delta":-70740,"detailPageLink":"https://www.ligainsider.de/jamie-leweling_21336/","kickbaseId":"2988"},{"lastName":"Daley Sinkgraven","delta":-70666,"detailPageLink":"https://www.ligainsider.de/daley-sinkgraven_11384/","kickbaseId":"2645"},{"lastName":"Arne Maier","delta":-70485,"detailPageLink":"https://www.ligainsider.de/arne-maier_10422/","kickbaseId":"2005"},{"lastName":"Ermedin Demirović","delta":-70393,"detailPageLink":"https://www.ligainsider.de/ermedin-demirovic_24166/","kickbaseId":"2854"},{"lastName":"Jorge Meré","delta":-69967,"detailPageLink":"https://www.ligainsider.de/jorge-mere_8921/","kickbaseId":"2118"},{"lastName":"Sargis Adamyan","delta":-69603,"detailPageLink":"https://www.ligainsider.de/sargis-adamyan_14085/","kickbaseId":"2426"},{"lastName":"Dedryck Boyata","delta":-69005,"detailPageLink":"https://www.ligainsider.de/dedryck-boyata_4748/","kickbaseId":"2676"},{"lastName":"Omar Richards","delta":-67334,"detailPageLink":"https://www.ligainsider.de/omar-richards_25804/","kickbaseId":"3006"},{"lastName":"André Silva","delta":-66429,"detailPageLink":"https://www.ligainsider.de/andre-silva_12204/","kickbaseId":"2747"},{"lastName":"Aarón","delta":-65267,"detailPageLink":"https://www.ligainsider.de/aaron-martin-caricol_20004/","kickbaseId":"2322"},{"lastName":"Manuel Gulde","delta":-64228,"detailPageLink":"https://www.ligainsider.de/manuel-gulde_347/","kickbaseId":"1138"},{"lastName":"John Anthony Brooks","delta":-64154,"detailPageLink":"https://www.ligainsider.de/john-anthony-brooks_684/","kickbaseId":"651"},{"lastName":"Mijat Gaćinović","delta":-60759,"detailPageLink":"https://www.ligainsider.de/mijat-gacinovic_6702/","kickbaseId":"1764"},{"lastName":"Jacob Laursen","delta":-60568,"detailPageLink":"https://www.ligainsider.de/jacob-barrett-laursen_24159/","kickbaseId":"2841"},{"lastName":"Felix Passlack","delta":-55291,"detailPageLink":"https://www.ligainsider.de/felix-passlack_6212/","kickbaseId":"1785"},{"lastName":"Santiago Ascacibar","delta":-54170,"detailPageLink":"https://www.ligainsider.de/santiago-ascacibar_13668/","kickbaseId":"2145"},{"lastName":"Marc Oliver Kempf","delta":-53200,"detailPageLink":"https://www.ligainsider.de/marc-oliver-kempf_2288/","kickbaseId":"99"},{"lastName":"Håvard Nielsen","delta":-49237,"detailPageLink":"https://www.ligainsider.de/havard-nielsen_3305/","kickbaseId":"1198"},{"lastName":"Piero Hincapié","delta":-48917,"detailPageLink":"https://www.ligainsider.de/piero-hincapie_26475/","kickbaseId":"3128"},{"lastName":"Lukas Klünter","delta":-47510,"detailPageLink":"https://www.ligainsider.de/lukas-kluenter_6199/","kickbaseId":"1763"},{"lastName":"Grischa Prömel","delta":-46824,"detailPageLink":"https://www.ligainsider.de/grischa-proemel_5816/","kickbaseId":"1671"},{"lastName":"Andreas Voglsammer","delta":-46330,"detailPageLink":"https://www.ligainsider.de/andreas-voglsammer_6233/","kickbaseId":"2631"},{"lastName":"Reinier","delta":-46172,"detailPageLink":"https://www.ligainsider.de/reinier-jesus-carvalho_20536/","kickbaseId":"2873"},{"lastName":"Takuma Asano","delta":-44603,"detailPageLink":"https://www.ligainsider.de/takuma-asano_7604/","kickbaseId":"2079"},{"lastName":"Mahmoud Dahoud","delta":-44566,"detailPageLink":"https://www.ligainsider.de/mahmoud-dahoud_2735/","kickbaseId":"736"},{"lastName":"Paul Seguin","delta":-42881,"detailPageLink":"https://www.ligainsider.de/paul-seguin_3655/","kickbaseId":"1207"},{"lastName":"Peter Pekarík","delta":-42112,"detailPageLink":"https://www.ligainsider.de/peter-pekarik_124/","kickbaseId":"693"},{"lastName":"Julian Green","delta":-41968,"detailPageLink":"https://www.ligainsider.de/julian-green_2729/","kickbaseId":"1187"},{"lastName":"Krzysztof Piątek","delta":-36596,"detailPageLink":"https://www.ligainsider.de/krzysztof-piatek_20290/","kickbaseId":"2780"},{"lastName":"Bouna Sarr","delta":-36096,"detailPageLink":"https://www.ligainsider.de/bouna-sarr_17152/","kickbaseId":"2915"},{"lastName":"Gonçalo Paciência","delta":-34791,"detailPageLink":"https://www.ligainsider.de/goncalo-paciencia_12176/","kickbaseId":"2287"},{"lastName":"Felix Uduokhai","delta":-27832,"detailPageLink":"https://www.ligainsider.de/ohis-felix-uduokhai_7041/","kickbaseId":"2065"},{"lastName":"Genki Haraguchi","delta":-24358,"detailPageLink":"https://www.ligainsider.de/genki-haraguchi_4527/","kickbaseId":"1571"},{"lastName":"Nicolas Höfler","delta":-20594,"detailPageLink":"https://www.ligainsider.de/nicolas-hoefler_619/","kickbaseId":"581"},{"lastName":"Nick Viergever","delta":-18586,"detailPageLink":"https://www.ligainsider.de/nick-viergever_11382/","kickbaseId":"3146"},{"lastName":"Josip Stanišić","delta":-17486,"detailPageLink":"https://www.ligainsider.de/josip-stanisic_20102/","kickbaseId":"2300"},{"lastName":"Niklas Dorsch","delta":-12068,"detailPageLink":"https://www.ligainsider.de/niklas-dorsch_6811/","kickbaseId":"1929"},{"lastName":"Exequiel Palacios","delta":-11733,"detailPageLink":"https://www.ligainsider.de/exequiel-palacios_20382/","kickbaseId":"2766"},{"lastName":"Kevin Trapp","delta":-6789,"detailPageLink":"https://www.ligainsider.de/kevin-trapp_636/","kickbaseId":"429"},{"lastName":"David Raum","delta":-4850,"detailPageLink":"https://www.ligainsider.de/david-raum_12557/","kickbaseId":"2522"},{"lastName":"Kristijan Jakić","delta":-4612,"detailPageLink":"https://www.ligainsider.de/kristijan-jakic_24599/","kickbaseId":"3143"},{"lastName":"Maximilian Philipp","delta":-4417,"detailPageLink":"https://www.ligainsider.de/maximilian-philipp_2246/","kickbaseId":"1226"}]}