{"date":"2021-10-31","players":[{"lastName":"Robert Skov","delta":688638,"detailPageLink":"https://www.ligainsider.de/robert-skov_18702/","kickbaseId":"2717"},{"lastName":"Hugo Novoa","delta":584053,"detailPageLink":"https://www.ligainsider.de/hugo-novoa_24140/","kickbaseId":"2868"},{"lastName":"Steffen Tigges","delta":542404,"detailPageLink":"https://www.ligainsider.de/steffen-tigges_15810/","kickbaseId":"2749"},{"lastName":"Aster Vranckx","delta":504829,"detailPageLink":"https://www.ligainsider.de/aster-vranckx_25757/","kickbaseId":"3004"},{"lastName":"Jamie Leweling","delta":451370,"detailPageLink":"https://www.ligainsider.de/jamie-leweling_21336/","kickbaseId":"2988"},{"lastName":"Danny Blum","delta":444905,"detailPageLink":"https://www.ligainsider.de/danny-blum_4533/","kickbaseId":"1506"},{"lastName":"Jae-sung Lee","delta":378854,"detailPageLink":"https://www.ligainsider.de/jae-sung-lee_21202/","kickbaseId":"2476"},{"lastName":"Takuma Asano","delta":373374,"detailPageLink":"https://www.ligainsider.de/takuma-asano_7604/","kickbaseId":"2079"},{"lastName":"Waldemar Anton","delta":370310,"detailPageLink":"https://www.ligainsider.de/waldemar-anton_5837/","kickbaseId":"1704"},{"lastName":"Hiroki Ito","delta":364386,"detailPageLink":"https://www.ligainsider.de/hiroki-ito_26128/","kickbaseId":"3089"},{"lastName":"Josuha Guilavogui","delta":358347,"detailPageLink":"https://www.ligainsider.de/josuha-guilavogui_2741/","kickbaseId":"1618"},{"lastName":"Xaver Schlager","delta":357317,"detailPageLink":"https://www.ligainsider.de/xaver-schlager_11547/","kickbaseId":"2649"},{"lastName":"Stefan Posch","delta":356794,"detailPageLink":"https://www.ligainsider.de/stefan-posch_12798/","kickbaseId":"2006"},{"lastName":"Karim Onisiwo","delta":356535,"detailPageLink":"https://www.ligainsider.de/karim-onisiwo_7011/","kickbaseId":"1804"},{"lastName":"Corentin Tolisso","delta":356258,"detailPageLink":"https://www.ligainsider.de/corentin-tolisso_12408/","kickbaseId":"2046"},{"lastName":"Thorgan Hazard","delta":356219,"detailPageLink":"https://www.ligainsider.de/thorgan-hazard_4196/","kickbaseId":"1583"},{"lastName":"Marius Wolf","delta":353438,"detailPageLink":"https://www.ligainsider.de/marius-wolf_5670/","kickbaseId":"1809"},{"lastName":"Dennis Geiger","delta":331919,"detailPageLink":"https://www.ligainsider.de/dennis-geiger_10434/","kickbaseId":"1990"},{"lastName":"Maximilian Eggestein","delta":314260,"detailPageLink":"https://www.ligainsider.de/maximilian-eggestein_6131/","kickbaseId":"1645"},{"lastName":"Thomas Meunier","delta":310676,"detailPageLink":"https://www.ligainsider.de/thomas-meunier_3667/","kickbaseId":"2835"},{"lastName":"Robert Andrich","delta":308319,"detailPageLink":"https://www.ligainsider.de/robert-andrich_2590/","kickbaseId":"663"},{"lastName":"Lucas Alario","delta":293768,"detailPageLink":"https://www.ligainsider.de/lucas-alario_5947/","kickbaseId":"2157"},{"lastName":"Ramy Bensebaini","delta":292339,"detailPageLink":"https://www.ligainsider.de/ramy-bensebaini_7791/","kickbaseId":"2736"},{"lastName":"Aarón","delta":291748,"detailPageLink":"https://www.ligainsider.de/aaron-martin-caricol_20004/","kickbaseId":"2322"},{"lastName":"Paul Jaeckel","delta":289713,"detailPageLink":"https://www.ligainsider.de/paul-jaeckel_13704/","kickbaseId":"2197"},{"lastName":"Youssoufa Moukoko","delta":284788,"detailPageLink":"https://www.ligainsider.de/youssoufa-moukoko_24068/","kickbaseId":"2866"},{"lastName":"Florian Müller","delta":283540,"detailPageLink":"https://www.ligainsider.de/florian-mueller_7609/","kickbaseId":"1910"},{"lastName":"Jonathan Burkardt","delta":283153,"detailPageLink":"https://www.ligainsider.de/jonathan-burkardt_19272/","kickbaseId":"2255"},{"lastName":"Silvan Widmer","delta":280187,"detailPageLink":"https://www.ligainsider.de/silvan-widmer_1938/","kickbaseId":"3041"},{"lastName":"Hamadi Al Ghaddioui","delta":272777,"detailPageLink":"https://www.ligainsider.de/hamadi-al-ghaddioui_10736/","kickbaseId":"2541"},{"lastName":"Erhan Mašović","delta":267552,"detailPageLink":"https://www.ligainsider.de/erhan-masovic_25008/","kickbaseId":"2994"},{"lastName":"David Nemeth","delta":265580,"detailPageLink":"https://www.ligainsider.de/david-nemeth_24642/","kickbaseId":"3014"},{"lastName":"Marin Pongračić","delta":264788,"detailPageLink":"https://www.ligainsider.de/marin-pongracic_13854/","kickbaseId":"2771"},{"lastName":"Alexander Hack","delta":263169,"detailPageLink":"https://www.ligainsider.de/alexander-hack_5877/","kickbaseId":"1789"},{"lastName":"Sebastian Rudy","delta":252959,"detailPageLink":"https://www.ligainsider.de/sebastian-rudy_188/","kickbaseId":"410"},{"lastName":"Stefan Lainer","delta":251904,"detailPageLink":"https://www.ligainsider.de/stefan-lainer_11546/","kickbaseId":"2644"},{"lastName":"Dejan Ljubičić","delta":246728,"detailPageLink":"https://www.ligainsider.de/dejan-ljubicic_24396/","kickbaseId":"3029"},{"lastName":"Lukas Nmecha","delta":245669,"detailPageLink":"https://www.ligainsider.de/lukas-nmecha_18385/","kickbaseId":"2724"},{"lastName":"Danilo Soares","delta":243749,"detailPageLink":"https://www.ligainsider.de/danilo-soares_5734/","kickbaseId":"1544"},{"lastName":"Florian Grillitsch","delta":243213,"detailPageLink":"https://www.ligainsider.de/florian-grillitsch_5385/","kickbaseId":"1703"},{"lastName":"Niklas Tauer","delta":236212,"detailPageLink":"https://www.ligainsider.de/niklas-tauer_20680/","kickbaseId":"2891"},{"lastName":"Daniel Didavi","delta":233893,"detailPageLink":"https://www.ligainsider.de/daniel-didavi_180/","kickbaseId":"469"},{"lastName":"Felix Passlack","delta":231670,"detailPageLink":"https://www.ligainsider.de/felix-passlack_6212/","kickbaseId":"1785"},{"lastName":"Santiago Ascacibar","delta":230770,"detailPageLink":"https://www.ligainsider.de/santiago-ascacibar_13668/","kickbaseId":"2145"},{"lastName":"Wahid Faghir","delta":230187,"detailPageLink":"https://www.ligainsider.de/wahid-faghir_26239/","kickbaseId":"3138"},{"lastName":"Sebastian Polter","delta":227323,"detailPageLink":"https://www.ligainsider.de/sebastian-polter_625/","kickbaseId":"496"},{"lastName":"Dominik Kohr","delta":223699,"detailPageLink":"https://www.ligainsider.de/dominik-kohr_1821/","kickbaseId":"60"},{"lastName":"Mark Uth","delta":222963,"detailPageLink":"https://www.ligainsider.de/mark-uth_469/","kickbaseId":"1725"},{"lastName":"Yannick Gerhardt","delta":218673,"detailPageLink":"https://www.ligainsider.de/yannick-gerhardt_3942/","kickbaseId":"1298"},{"lastName":"Sheraldo Becker","delta":210283,"detailPageLink":"https://www.ligainsider.de/sheraldo-becker_20640/","kickbaseId":"2646"},{"lastName":"Orel Mangala","delta":204584,"detailPageLink":"https://www.ligainsider.de/orel-mangala_7078/","kickbaseId":"2049"},{"lastName":"Kingsley Coman","delta":204377,"detailPageLink":"https://www.ligainsider.de/kingsley-coman_6690/","kickbaseId":"1774"},{"lastName":"Kevin Vogt","delta":202354,"detailPageLink":"https://www.ligainsider.de/kevin-vogt_209/","kickbaseId":"477"},{"lastName":"Marco Richter","delta":200764,"detailPageLink":"https://www.ligainsider.de/marco-richter_12774/","kickbaseId":"2092"},{"lastName":"Diadié Samassékou","delta":198187,"detailPageLink":"https://www.ligainsider.de/diadie-samassekou_11545/","kickbaseId":"2737"},{"lastName":"Genki Haraguchi","delta":196555,"detailPageLink":"https://www.ligainsider.de/genki-haraguchi_4527/","kickbaseId":"1571"},{"lastName":"Woo-yeong Jeong","delta":194488,"detailPageLink":"https://www.ligainsider.de/woo-yeong-jeong_14145/","kickbaseId":"2302"},{"lastName":"Reece Oxford","delta":191533,"detailPageLink":"https://www.ligainsider.de/reece-oxford_9583/","kickbaseId":"2047"},{"lastName":"Alfreð Finnbogason","delta":191369,"detailPageLink":"https://www.ligainsider.de/alfred-finnbogason_2658/","kickbaseId":"1826"},{"lastName":"Robin Zentner","delta":189534,"detailPageLink":"https://www.ligainsider.de/robin-zentner_3298/","kickbaseId":"1590"},{"lastName":"Dominik Szoboszlai","delta":186912,"detailPageLink":"https://www.ligainsider.de/dominik-szoboszlai_18934/","kickbaseId":"2940"},{"lastName":"Marcus Thuram","delta":183816,"detailPageLink":"https://www.ligainsider.de/marcus-thuram_20516/","kickbaseId":"2704"},{"lastName":"Timothy Fosu-Mensah","delta":183141,"detailPageLink":"https://www.ligainsider.de/timothy-fosu-mensah_7481/","kickbaseId":"2944"},{"lastName":"Kevin Akpoguma","delta":181051,"detailPageLink":"https://www.ligainsider.de/kevin-akpoguma_2477/","kickbaseId":"96"},{"lastName":"Jean-Paul Boëtius","delta":180230,"detailPageLink":"https://www.ligainsider.de/jean-paul-boetius_12328/","kickbaseId":"2339"},{"lastName":"Ihlas Bebou","delta":179763,"detailPageLink":"https://www.ligainsider.de/ihlas-bebou_4544/","kickbaseId":"1308"},{"lastName":"Josip Stanišić","delta":178558,"detailPageLink":"https://www.ligainsider.de/josip-stanisic_20102/","kickbaseId":"2300"},{"lastName":"Christoph Baumgartner","delta":177766,"detailPageLink":"https://www.ligainsider.de/christoph-baumgartner_18640/","kickbaseId":"2275"},{"lastName":"Nordi Mukiele","delta":177632,"detailPageLink":"https://www.ligainsider.de/nordi-mukiele_18662/","kickbaseId":"2241"},{"lastName":"Yussuf Poulsen","delta":170256,"detailPageLink":"https://www.ligainsider.de/yussuf-poulsen_5765/","kickbaseId":"1865"},{"lastName":"Kevin Mbabu","delta":170111,"detailPageLink":"https://www.ligainsider.de/kevin-mbabu_6856/","kickbaseId":"2639"},{"lastName":"Stefan Bell","delta":165727,"detailPageLink":"https://www.ligainsider.de/stefan-bell_521/","kickbaseId":"550"},{"lastName":"Maximilian Arnold","delta":164638,"detailPageLink":"https://www.ligainsider.de/maximilian-arnold_1673/","kickbaseId":"44"},{"lastName":"Georginio Rutter","delta":159560,"detailPageLink":"https://www.ligainsider.de/georginio-rutter_25119/","kickbaseId":"2949"},{"lastName":"Jacob Laursen","delta":158991,"detailPageLink":"https://www.ligainsider.de/jacob-barrett-laursen_24159/","kickbaseId":"2841"},{"lastName":"Anthony Modeste","delta":158436,"detailPageLink":"https://www.ligainsider.de/anthony-modeste_1223/","kickbaseId":"684"},{"lastName":"Paulinho","delta":158216,"detailPageLink":"https://www.ligainsider.de/paulinho_19078/","kickbaseId":"2291"},{"lastName":"Tomas Ostrak","delta":155734,"detailPageLink":"https://www.ligainsider.de/tomas-ostrak_18674/","kickbaseId":"3028"},{"lastName":"Vasilios Lampropoulos","delta":155384,"detailPageLink":"https://www.ligainsider.de/vasilios-lampropoulos_16396/","kickbaseId":"2997"},{"lastName":"Mats Hummels","delta":154615,"detailPageLink":"https://www.ligainsider.de/mats-hummels_131/","kickbaseId":"304"},{"lastName":"Lukas Kübler","delta":152675,"detailPageLink":"https://www.ligainsider.de/lukas-kuebler_1935/","kickbaseId":"1257"},{"lastName":"Philipp Lienhart","delta":152112,"detailPageLink":"https://www.ligainsider.de/philipp-lienhart_13911/","kickbaseId":"2084"},{"lastName":"Willi Orbán","delta":151279,"detailPageLink":"https://www.ligainsider.de/willi-orban_1667/","kickbaseId":"1246"},{"lastName":"Tuta","delta":150046,"detailPageLink":"https://www.ligainsider.de/lucas-silva-melo_20444/","kickbaseId":"2378"},{"lastName":"Ridle Baku","delta":147892,"detailPageLink":"https://www.ligainsider.de/ridle-baku_15835/","kickbaseId":"2141"},{"lastName":"Manuel Akanji","delta":146954,"detailPageLink":"https://www.ligainsider.de/manuel-akanji_12321/","kickbaseId":"2181"},{"lastName":"John Anthony Brooks","delta":146156,"detailPageLink":"https://www.ligainsider.de/john-anthony-brooks_684/","kickbaseId":"651"},{"lastName":"Vincenzo Grifo","delta":145163,"detailPageLink":"https://www.ligainsider.de/vincenzo-grifo_2361/","kickbaseId":"118"},{"lastName":"Julian Green","delta":142843,"detailPageLink":"https://www.ligainsider.de/julian-green_2729/","kickbaseId":"1187"},{"lastName":"Borna Sosa","delta":139186,"detailPageLink":"https://www.ligainsider.de/borna-sosa_12284/","kickbaseId":"2247"},{"lastName":"Maximilian Mittelstädt","delta":130230,"detailPageLink":"https://www.ligainsider.de/maximilian-mittelstaedt_6206/","kickbaseId":"1664"},{"lastName":"Rani Khedira","delta":129874,"detailPageLink":"https://www.ligainsider.de/rani-khedira_2122/","kickbaseId":"51"},{"lastName":"Manuel Neuer","delta":128946,"detailPageLink":"https://www.ligainsider.de/manuel-neuer_114/","kickbaseId":"237"},{"lastName":"Jude Bellingham","delta":126829,"detailPageLink":"https://www.ligainsider.de/jude-bellingham_24076/","kickbaseId":"2845"},{"lastName":"Oliver Baumann","delta":126616,"detailPageLink":"https://www.ligainsider.de/oliver-baumann_567/","kickbaseId":"524"},{"lastName":"Thomas Müller","delta":126353,"detailPageLink":"https://www.ligainsider.de/thomas-mueller_249/","kickbaseId":"450"},{"lastName":"Rafael Santos Borré","delta":122243,"detailPageLink":"https://www.ligainsider.de/rafael-santos-borre_12083/","kickbaseId":"3030"},{"lastName":"Cristian Gamboa","delta":121154,"detailPageLink":"https://www.ligainsider.de/cristian-gamboa_994/","kickbaseId":"2990"},{"lastName":"Lars Stindl","delta":118980,"detailPageLink":"https://www.ligainsider.de/lars-stindl_487/","kickbaseId":"393"},{"lastName":"Daniel Caligiuri","delta":116673,"detailPageLink":"https://www.ligainsider.de/daniel-caligiuri_274/","kickbaseId":"542"},{"lastName":"Matthias Ginter","delta":116271,"detailPageLink":"https://www.ligainsider.de/matthias-ginter_1835/","kickbaseId":"49"},{"lastName":"Jamal Musiala","delta":116186,"detailPageLink":"https://www.ligainsider.de/jamal-musiala_24149/","kickbaseId":"2804"},{"lastName":"Dayot Upamecano","delta":113244,"detailPageLink":"https://www.ligainsider.de/dayot-upamecano_11541/","kickbaseId":"1991"},{"lastName":"Raphaël Guerreiro","delta":112598,"detailPageLink":"https://www.ligainsider.de/raphael-guerreiro_6795/","kickbaseId":"1862"},{"lastName":"Marwin Hitz","delta":112589,"detailPageLink":"https://www.ligainsider.de/marwin-hitz_639/","kickbaseId":"454"},{"lastName":"Manuel Riemann","delta":110560,"detailPageLink":"https://www.ligainsider.de/manuel-riemann_5895/","kickbaseId":"1405"},{"lastName":"Ruben Vargas","delta":109110,"detailPageLink":"https://www.ligainsider.de/ruben-vargas_20532/","kickbaseId":"2664"},{"lastName":"Lucas Höler","delta":108008,"detailPageLink":"https://www.ligainsider.de/lucas-hoeler_6593/","kickbaseId":"2176"},{"lastName":"Rafał Gikiewicz","delta":107752,"detailPageLink":"https://www.ligainsider.de/rafal-gikiewicz_4199/","kickbaseId":"1936"},{"lastName":"Alassane Pléa","delta":106825,"detailPageLink":"https://www.ligainsider.de/alassane-plea_11770/","kickbaseId":"2288"},{"lastName":"Konstantinos Mavropanos","delta":104205,"detailPageLink":"https://www.ligainsider.de/konstantinos-mavropanos_18854/","kickbaseId":"2838"},{"lastName":"Niko Gießelmann","delta":103921,"detailPageLink":"https://www.ligainsider.de/niko-giesselmann_2232/","kickbaseId":"102"},{"lastName":"Julian Brandt","delta":103785,"detailPageLink":"https://www.ligainsider.de/julian-brandt_2467/","kickbaseId":"1192"},{"lastName":"Koen Casteels","delta":100762,"detailPageLink":"https://www.ligainsider.de/koen-casteels_1605/","kickbaseId":"497"},{"lastName":"Keven Schlotterbeck","delta":99373,"detailPageLink":"https://www.ligainsider.de/keven-schlotterbeck_19286/","kickbaseId":"2274"},{"lastName":"Christian Günter","delta":94811,"detailPageLink":"https://www.ligainsider.de/christian-guenter_2153/","kickbaseId":"89"},{"lastName":"Edmond Tapsoba","delta":92084,"detailPageLink":"https://www.ligainsider.de/edmond-tapsoba_19022/","kickbaseId":"2783"},{"lastName":"Andrej Kramarić","delta":91755,"detailPageLink":"https://www.ligainsider.de/andrej-kramaric_2439/","kickbaseId":"1815"},{"lastName":"Manu Koné","delta":91152,"detailPageLink":"https://www.ligainsider.de/emmanuel-kouadio-kone_25803/","kickbaseId":"3011"},{"lastName":"Nicolas Höfler","delta":87339,"detailPageLink":"https://www.ligainsider.de/nicolas-hoefler_619/","kickbaseId":"581"},{"lastName":"Benjamin Pavard","delta":84713,"detailPageLink":"https://www.ligainsider.de/benjamin-pavard_11327/","kickbaseId":"2054"},{"lastName":"Axel Witsel","delta":83569,"detailPageLink":"https://www.ligainsider.de/axel-witsel_4551/","kickbaseId":"2323"},{"lastName":"Nico Elvedi","delta":82084,"detailPageLink":"https://www.ligainsider.de/nico-elvedi_6475/","kickbaseId":"1686"},{"lastName":"Serge Gnabry","delta":80933,"detailPageLink":"https://www.ligainsider.de/serge-gnabry_4815/","kickbaseId":"1961"},{"lastName":"Taiwo Awoniyi","delta":80445,"detailPageLink":"https://www.ligainsider.de/taiwo-awoniyi_6805/","kickbaseId":"2729"},{"lastName":"Nadiem Amiri","delta":79406,"detailPageLink":"https://www.ligainsider.de/nadiem-amiri_5815/","kickbaseId":"1639"},{"lastName":"Saša Kalajdžić","delta":78539,"detailPageLink":"https://www.ligainsider.de/sasa-kalajdzic_20605/","kickbaseId":"2819"},{"lastName":"Dani Olmo","delta":77612,"detailPageLink":"https://www.ligainsider.de/dani-olmo_12291/","kickbaseId":"2776"},{"lastName":"Dodi Lukébakio","delta":74016,"detailPageLink":"https://www.ligainsider.de/dodi-lukebakio_11859/","kickbaseId":"2308"},{"lastName":"Timo Baumgartl","delta":71783,"detailPageLink":"https://www.ligainsider.de/timo-baumgartl_3284/","kickbaseId":"1584"},{"lastName":"Renato Steffen","delta":69912,"detailPageLink":"https://www.ligainsider.de/renato-steffen_7785/","kickbaseId":"2179"},{"lastName":"Anthony Losilla","delta":68381,"detailPageLink":"https://www.ligainsider.de/anthony-losilla_5649/","kickbaseId":"1514"},{"lastName":"Leandro Barreiro","delta":66391,"detailPageLink":"https://www.ligainsider.de/leandro-barreiro-martins_19288/","kickbaseId":"2335"},{"lastName":"Jonas Hector","delta":64919,"detailPageLink":"https://www.ligainsider.de/jonas-hector_1936/","kickbaseId":"1256"},{"lastName":"Denis Zakaria","delta":64675,"detailPageLink":"https://www.ligainsider.de/denis-zakaria_7664/","kickbaseId":"2063"},{"lastName":"Gregor Kobel","delta":63317,"detailPageLink":"https://www.ligainsider.de/gregor-kobel_9357/","kickbaseId":"1873"},{"lastName":"Mark Flekken","delta":62511,"detailPageLink":"https://www.ligainsider.de/mark-flekken_4530/","kickbaseId":"72"},{"lastName":"Omar Richards","delta":61309,"detailPageLink":"https://www.ligainsider.de/omar-richards_25804/","kickbaseId":"3006"},{"lastName":"Daichi Kamada","delta":61214,"detailPageLink":"https://www.ligainsider.de/daichi-kamada_14160/","kickbaseId":"2059"},{"lastName":"Emil Forsberg","delta":61171,"detailPageLink":"https://www.ligainsider.de/emil-forsberg_6158/","kickbaseId":"1900"},{"lastName":"Leroy Sané","delta":59964,"detailPageLink":"https://www.ligainsider.de/leroy-sane_3798/","kickbaseId":"1222"},{"lastName":"Breel Embolo","delta":59131,"detailPageLink":"https://www.ligainsider.de/breel-embolo_6091/","kickbaseId":"1869"},{"lastName":"Mohamed Simakan","delta":58796,"detailPageLink":"https://www.ligainsider.de/mohamed-simakan_24093/","kickbaseId":"3001"},{"lastName":"Marco Reus","delta":58411,"detailPageLink":"https://www.ligainsider.de/marco-reus_332/","kickbaseId":"399"},{"lastName":"Amadou Haidara","delta":57961,"detailPageLink":"https://www.ligainsider.de/amadou-haidara_16768/","kickbaseId":"2365"},{"lastName":"Branimir Hrgota","delta":56444,"detailPageLink":"https://www.ligainsider.de/branimir-hrgota_2169/","kickbaseId":"84"},{"lastName":"Niklas Süle","delta":55780,"detailPageLink":"https://www.ligainsider.de/niklas-suele_2584/","kickbaseId":"163"},{"lastName":"Marc Oliver Kempf","delta":52718,"detailPageLink":"https://www.ligainsider.de/marc-oliver-kempf_2288/","kickbaseId":"99"},{"lastName":"Wout Weghorst","delta":52125,"detailPageLink":"https://www.ligainsider.de/wout-weghorst_11463/","kickbaseId":"2229"},{"lastName":"Alphonso Davies","delta":49054,"detailPageLink":"https://www.ligainsider.de/alphonso-davies_20098/","kickbaseId":"2366"},{"lastName":"Christopher Trimmel","delta":47596,"detailPageLink":"https://www.ligainsider.de/christopher-trimmel_5713/","kickbaseId":"2400"},{"lastName":"Jonas Hofmann","delta":46149,"detailPageLink":"https://www.ligainsider.de/jonas-hofmann_2362/","kickbaseId":"78"},{"lastName":"Niklas Stark","delta":43946,"detailPageLink":"https://www.ligainsider.de/niklas-stark_2441/","kickbaseId":"157"},{"lastName":"Moussa Niakhaté","delta":43650,"detailPageLink":"https://www.ligainsider.de/moussa-niakhate_19258/","kickbaseId":"2284"},{"lastName":"Tobias Strobl","delta":41403,"detailPageLink":"https://www.ligainsider.de/tobias-strobl_1461/","kickbaseId":"653"},{"lastName":"Linus Gechter","delta":41250,"detailPageLink":"https://www.ligainsider.de/linus-gechter_26139/","kickbaseId":"3097"},{"lastName":"Bryan Lasme","delta":39720,"detailPageLink":"https://www.ligainsider.de/bryan-lasme_26131/","kickbaseId":"3022"},{"lastName":"Ellyes Skhiri","delta":39502,"detailPageLink":"https://www.ligainsider.de/ellyes-skhiri_20776/","kickbaseId":"2718"},{"lastName":"Stefan Ortega Moreno","delta":37264,"detailPageLink":"https://www.ligainsider.de/stefan-ortega-moreno_1905/","kickbaseId":"1163"},{"lastName":"Elvis Rexhbeçaj","delta":35768,"detailPageLink":"https://www.ligainsider.de/elvis-rexhbecaj_13707/","kickbaseId":"2091"},{"lastName":"Christopher Nkunku","delta":34628,"detailPageLink":"https://www.ligainsider.de/christopher-nkunku_12446/","kickbaseId":"2687"},{"lastName":"Marcel Sabitzer","delta":28769,"detailPageLink":"https://www.ligainsider.de/marcel-sabitzer_2020/","kickbaseId":"1856"},{"lastName":"André Hahn","delta":27546,"detailPageLink":"https://www.ligainsider.de/andre-hahn_2493/","kickbaseId":"570"},{"lastName":"Jonathan Tah","delta":26604,"detailPageLink":"https://www.ligainsider.de/jonathan-tah_2385/","kickbaseId":"173"},{"lastName":"Suat Serdar","delta":26384,"detailPageLink":"https://www.ligainsider.de/suat-serdar_6225/","kickbaseId":"1790"},{"lastName":"Chris Richards","delta":25988,"detailPageLink":"https://www.ligainsider.de/chris-richards_20104/","kickbaseId":"2298"},{"lastName":"Paulo Otávio","delta":25115,"detailPageLink":"https://www.ligainsider.de/paulo-otavio_12680/","kickbaseId":"2447"},{"lastName":"Jeffrey Gouweleeuw","delta":24704,"detailPageLink":"https://www.ligainsider.de/jeffrey-gouweleeuw_1851/","kickbaseId":"1811"},{"lastName":"Luca Kilian","delta":22537,"detailPageLink":"https://www.ligainsider.de/luca-kilian_20577/","kickbaseId":"2349"},{"lastName":"Kerem Demirbay","delta":21330,"detailPageLink":"https://www.ligainsider.de/kerem-demirbay_2486/","kickbaseId":"81"},{"lastName":"Marvin Friedrich","delta":21267,"detailPageLink":"https://www.ligainsider.de/marvin-friedrich_3296/","kickbaseId":"1223"},{"lastName":"Andreas Luthe","delta":20331,"detailPageLink":"https://www.ligainsider.de/andreas-luthe_172/","kickbaseId":"1116"},{"lastName":"Florian Wirtz","delta":19023,"detailPageLink":"https://www.ligainsider.de/florian-wirtz_23890/","kickbaseId":"2795"},{"lastName":"Joshua Kimmich","delta":18693,"detailPageLink":"https://www.ligainsider.de/joshua-kimmich_5768/","kickbaseId":"1685"},{"lastName":"Robert Lewandowski","delta":18364,"detailPageLink":"https://www.ligainsider.de/robert-lewandowski_366/","kickbaseId":"455"},{"lastName":"Nico Schlotterbeck","delta":16175,"detailPageLink":"https://www.ligainsider.de/nico-schlotterbeck_20052/","kickbaseId":"2383"},{"lastName":"Peter Pekarík","delta":13289,"detailPageLink":"https://www.ligainsider.de/peter-pekarik_124/","kickbaseId":"693"},{"lastName":"Ondrej Duda","delta":12143,"detailPageLink":"https://www.ligainsider.de/ondrej-duda_6360/","kickbaseId":"1919"},{"lastName":"Márton Dárdai","delta":6252,"detailPageLink":"https://www.ligainsider.de/marton-dardai_24119/","kickbaseId":"2796"},{"lastName":"Leon Goretzka","delta":4733,"detailPageLink":"https://www.ligainsider.de/leon-goretzka_1863/","kickbaseId":"660"},{"lastName":"Jeremie Frimpong","delta":4119,"detailPageLink":"https://www.ligainsider.de/jeremie-frimpong_22308/","kickbaseId":"2948"},{"lastName":"Erling Braut Haaland","delta":-813565,"detailPageLink":"https://www.ligainsider.de/erling-braut-haaland_20212/","kickbaseId":"2767"},{"lastName":"Patrik Schick","delta":-768956,"detailPageLink":"https://www.ligainsider.de/patrik-schick_7794/","kickbaseId":"2746"},{"lastName":"André Silva","delta":-642932,"detailPageLink":"https://www.ligainsider.de/andre-silva_12204/","kickbaseId":"2747"},{"lastName":"Max Kruse","delta":-589372,"detailPageLink":"https://www.ligainsider.de/max-kruse_482/","kickbaseId":"369"},{"lastName":"Jordan Beyer","delta":-553664,"detailPageLink":"https://www.ligainsider.de/louis-jordan-beyer_14448/","kickbaseId":"2193"},{"lastName":"Lukas Klostermann","delta":-506861,"detailPageLink":"https://www.ligainsider.de/lukas-klostermann_5622/","kickbaseId":"1333"},{"lastName":"Emre Can","delta":-486113,"detailPageLink":"https://www.ligainsider.de/emre-can_1812/","kickbaseId":"54"},{"lastName":"Odilon Kossounou","delta":-456640,"detailPageLink":"https://www.ligainsider.de/odilon-kossounou_22070/","kickbaseId":"3079"},{"lastName":"Djibril Sow","delta":-425759,"detailPageLink":"https://www.ligainsider.de/djibril-sow_6510/","kickbaseId":"1738"},{"lastName":"Giovanni Reyna","delta":-417349,"detailPageLink":"https://www.ligainsider.de/giovanni-reyna_20760/","kickbaseId":"2692"},{"lastName":"Kevin Kampl","delta":-409242,"detailPageLink":"https://www.ligainsider.de/kevin-kampl_942/","kickbaseId":"1653"},{"lastName":"Benno Schmitz","delta":-409196,"detailPageLink":"https://www.ligainsider.de/benno-schmitz_2731/","kickbaseId":"1229"},{"lastName":"Martin Hinteregger","delta":-383628,"detailPageLink":"https://www.ligainsider.de/martin-hinteregger_1293/","kickbaseId":"1810"},{"lastName":"Amine Adli","delta":-358966,"detailPageLink":"https://www.ligainsider.de/amine-adli_26134/","kickbaseId":"3132"},{"lastName":"Dedryck Boyata","delta":-357752,"detailPageLink":"https://www.ligainsider.de/dedryck-boyata_4748/","kickbaseId":"2676"},{"lastName":"Donyell Malen","delta":-355279,"detailPageLink":"https://www.ligainsider.de/donyell-malen_22986/","kickbaseId":"3087"},{"lastName":"Myziane Maolida","delta":-339420,"detailPageLink":"https://www.ligainsider.de/myziane-maolida_17104/","kickbaseId":"3145"},{"lastName":"David Raum","delta":-335289,"detailPageLink":"https://www.ligainsider.de/david-raum_12557/","kickbaseId":"2522"},{"lastName":"Atakan Karazor","delta":-316037,"detailPageLink":"https://www.ligainsider.de/atakan-karazor_10442/","kickbaseId":"2214"},{"lastName":"Luca Waldschmidt","delta":-314044,"detailPageLink":"https://www.ligainsider.de/luca-waldschmidt_2594/","kickbaseId":"737"},{"lastName":"Jesper Lindstrøm","delta":-310583,"detailPageLink":"https://www.ligainsider.de/jesper-lindstroem_26157/","kickbaseId":"3044"},{"lastName":"Evan N'Dicka","delta":-304065,"detailPageLink":"https://www.ligainsider.de/obite-evan-n-dicka_20006/","kickbaseId":"2282"},{"lastName":"Sam Lammers","delta":-298472,"detailPageLink":"https://www.ligainsider.de/sam-lammers_13251/","kickbaseId":"3144"},{"lastName":"Sebastian Andersson","delta":-296541,"detailPageLink":"https://www.ligainsider.de/sebastian-andersson_15907/","kickbaseId":"2394"},{"lastName":"Kristijan Jakić","delta":-293135,"detailPageLink":"https://www.ligainsider.de/kristijan-jakic_24599/","kickbaseId":"3143"},{"lastName":"Omar Marmoush","delta":-291655,"detailPageLink":"https://www.ligainsider.de/omar-marmoush_20690/","kickbaseId":"2792"},{"lastName":"Marcus Ingvartsen","delta":-288104,"detailPageLink":"https://www.ligainsider.de/marcus-ingvartsen_12598/","kickbaseId":"2642"},{"lastName":"Andi Zeqiri","delta":-284598,"detailPageLink":"https://www.ligainsider.de/andi-zeqiri_26572/","kickbaseId":"3137"},{"lastName":"Mitchel Bakker","delta":-281917,"detailPageLink":"https://www.ligainsider.de/mitchel-bakker_21916/","kickbaseId":"3046"},{"lastName":"Charles Aránguiz","delta":-267937,"detailPageLink":"https://www.ligainsider.de/charles-aranguiz_5279/","kickbaseId":"1766"},{"lastName":"Filip Kostić","delta":-267709,"detailPageLink":"https://www.ligainsider.de/filip-kostic_5808/","kickbaseId":"1620"},{"lastName":"Jeremiah St. Juste","delta":-266780,"detailPageLink":"https://www.ligainsider.de/jeremiah-st-juste_16064/","kickbaseId":"2728"},{"lastName":"Jacob Bruun Larsen","delta":-265745,"detailPageLink":"https://www.ligainsider.de/jacob-bruun-larsen_6837/","kickbaseId":"1781"},{"lastName":"Jurgen Ekkelenkamp","delta":-264400,"detailPageLink":"https://www.ligainsider.de/jurgen-ekkelenkamp_22044/","kickbaseId":"3135"},{"lastName":"Armel Bella-Kotchap","delta":-257057,"detailPageLink":"https://www.ligainsider.de/armel-bella-kotchap_20048/","kickbaseId":"2590"},{"lastName":"Pavel Kadeřábek","delta":-249808,"detailPageLink":"https://www.ligainsider.de/pavel-kade-abek_6340/","kickbaseId":"1726"},{"lastName":"Rafael Czichos","delta":-249403,"detailPageLink":"https://www.ligainsider.de/rafael-czichos_13983/","kickbaseId":"2209"},{"lastName":"Chris Führich","delta":-247222,"detailPageLink":"https://www.ligainsider.de/chris-fuehrich_18542/","kickbaseId":"2172"},{"lastName":"Tyler Adams","delta":-245077,"detailPageLink":"https://www.ligainsider.de/tyler-adams_14025/","kickbaseId":"2364"},{"lastName":"Angeliño","delta":-241934,"detailPageLink":"https://www.ligainsider.de/angelino_7472/","kickbaseId":"2779"},{"lastName":"Kevin Möhwald","delta":-240822,"detailPageLink":"https://www.ligainsider.de/kevin-moehwald_6096/","kickbaseId":"1841"},{"lastName":"Jérôme Roussillon","delta":-239761,"detailPageLink":"https://www.ligainsider.de/jerome-roussillon_14541/","kickbaseId":"2321"},{"lastName":"Sebastian Rode","delta":-239597,"detailPageLink":"https://www.ligainsider.de/sebastian-rode_451/","kickbaseId":"392"},{"lastName":"Lukáš Hrádecký","delta":-238818,"detailPageLink":"https://www.ligainsider.de/lukas-hradecky_6694/","kickbaseId":"1761"},{"lastName":"Tanguy Coulibaly","delta":-229771,"detailPageLink":"https://www.ligainsider.de/tanguy-coulibaly_21572/","kickbaseId":"2824"},{"lastName":"Kevin Trapp","delta":-227339,"detailPageLink":"https://www.ligainsider.de/kevin-trapp_636/","kickbaseId":"429"},{"lastName":"E. Choupo-Moting","delta":-220958,"detailPageLink":"https://www.ligainsider.de/eric-maxim-choupo-moting_430/","kickbaseId":"336"},{"lastName":"Eduard Löwen","delta":-213929,"detailPageLink":"https://www.ligainsider.de/eduard-loewen_13671/","kickbaseId":"2254"},{"lastName":"Erik Durm","delta":-212944,"detailPageLink":"https://www.ligainsider.de/erik-durm_1847/","kickbaseId":"732"},{"lastName":"Luca Netz","delta":-211572,"detailPageLink":"https://www.ligainsider.de/luca-netz_24118/","kickbaseId":"2799"},{"lastName":"Florian Neuhaus","delta":-211434,"detailPageLink":"https://www.ligainsider.de/florian-neuhaus_10416/","kickbaseId":"2261"},{"lastName":"Lucas Hernández","delta":-210736,"detailPageLink":"https://www.ligainsider.de/lucas-hernandez_12218/","kickbaseId":"2647"},{"lastName":"Manuel Gulde","delta":-209675,"detailPageLink":"https://www.ligainsider.de/manuel-gulde_347/","kickbaseId":"1138"},{"lastName":"Jonathan Schmid","delta":-207116,"detailPageLink":"https://www.ligainsider.de/jonathan-schmid_641/","kickbaseId":"605"},{"lastName":"Salih Özcan","delta":-205773,"detailPageLink":"https://www.ligainsider.de/salih-oezcan_6816/","kickbaseId":"1918"},{"lastName":"Florian Kainz","delta":-202134,"detailPageLink":"https://www.ligainsider.de/florian-kainz_6982/","kickbaseId":"1903"},{"lastName":"Péter Gulácsi","delta":-200364,"detailPageLink":"https://www.ligainsider.de/peter-gulacsi_6429/","kickbaseId":"1896"},{"lastName":"Fabian Klos","delta":-193447,"detailPageLink":"https://www.ligainsider.de/fabian-klos_1448/","kickbaseId":"1115"},{"lastName":"Marvin Plattenhardt","delta":-191994,"detailPageLink":"https://www.ligainsider.de/marvin-plattenhardt_581/","kickbaseId":"600"},{"lastName":"Silas","delta":-189583,"detailPageLink":"https://www.ligainsider.de/silas-katompa-mvumpa_21594/","kickbaseId":"2822"},{"lastName":"Robin Knoche","delta":-188027,"detailPageLink":"https://www.ligainsider.de/robin-knoche_1629/","kickbaseId":"623"},{"lastName":"Yann Sommer","delta":-182980,"detailPageLink":"https://www.ligainsider.de/yann-sommer_2577/","kickbaseId":"1568"},{"lastName":"Jens Petter Hauge","delta":-170599,"detailPageLink":"https://www.ligainsider.de/jens-petter-hauge_25321/","kickbaseId":"3125"},{"lastName":"Mahmoud Dahoud","delta":-148485,"detailPageLink":"https://www.ligainsider.de/mahmoud-dahoud_2735/","kickbaseId":"736"},{"lastName":"Exequiel Palacios","delta":-141321,"detailPageLink":"https://www.ligainsider.de/exequiel-palacios_20382/","kickbaseId":"2766"},{"lastName":"Lennart Czyborra","delta":-140766,"detailPageLink":"https://www.ligainsider.de/lennart-czyborra_18576/","kickbaseId":"3134"},{"lastName":"Konrad Laimer","delta":-135960,"detailPageLink":"https://www.ligainsider.de/konrad-laimer_6324/","kickbaseId":"2038"},{"lastName":"Nico Schulz","delta":-135072,"detailPageLink":"https://www.ligainsider.de/nico-schulz_675/","kickbaseId":"726"},{"lastName":"Sebastian Griesbeck","delta":-134103,"detailPageLink":"https://www.ligainsider.de/sebastian-griesbeck_5791/","kickbaseId":"2432"},{"lastName":"Raphael Framberger","delta":-131061,"detailPageLink":"https://www.ligainsider.de/raphael-framberger_2470/","kickbaseId":"668"},{"lastName":"Wataru Endo","delta":-130894,"detailPageLink":"https://www.ligainsider.de/wataru-endo_23590/","kickbaseId":"2837"},{"lastName":"Cedric Teuchert","delta":-129199,"detailPageLink":"https://www.ligainsider.de/cedric-teuchert_6095/","kickbaseId":"1842"},{"lastName":"Mijat Gaćinović","delta":-129129,"detailPageLink":"https://www.ligainsider.de/mijat-gacinovic_6702/","kickbaseId":"1764"},{"lastName":"Jordan Torunarigha","delta":-128107,"detailPageLink":"https://www.ligainsider.de/jordan-torunarigha_6513/","kickbaseId":"1978"},{"lastName":"Marius Funk","delta":-128018,"detailPageLink":"https://www.ligainsider.de/marius-funk_5936/","kickbaseId":"2445"},{"lastName":"Cedric Itten","delta":-127711,"detailPageLink":"https://www.ligainsider.de/cedric-itten_18071/","kickbaseId":"3139"},{"lastName":"Jetro Willems","delta":-126372,"detailPageLink":"https://www.ligainsider.de/jetro-willems_6854/","kickbaseId":"2121"},{"lastName":"Nick Viergever","delta":-126109,"detailPageLink":"https://www.ligainsider.de/nick-viergever_11382/","kickbaseId":"3146"},{"lastName":"Marco Meyerhöfer","delta":-126080,"detailPageLink":"https://www.ligainsider.de/marco-meyerhoefer_7637/","kickbaseId":"2985"},{"lastName":"Noah Weißhaupt","delta":-125512,"detailPageLink":"https://www.ligainsider.de/noah-weisshaupt_23598/","kickbaseId":"3017"},{"lastName":"Kingsley Schindler","delta":-124379,"detailPageLink":"https://www.ligainsider.de/kingsley-schindler_3556/","kickbaseId":"2213"},{"lastName":"Sebastian Vasiliadis","delta":-124312,"detailPageLink":"https://www.ligainsider.de/sebastian-vasiliadis_19076/","kickbaseId":"2502"},{"lastName":"Levin Öztunali","delta":-122395,"detailPageLink":"https://www.ligainsider.de/levin-oeztunali_2466/","kickbaseId":"672"},{"lastName":"Anton Stach","delta":-122326,"detailPageLink":"https://www.ligainsider.de/anton-stach_20696/","kickbaseId":"2987"},{"lastName":"Kevin-Prince Boateng","delta":-122207,"detailPageLink":"https://www.ligainsider.de/kevin-prince-boateng_2352/","kickbaseId":"749"},{"lastName":"Davie Selke","delta":-121777,"detailPageLink":"https://www.ligainsider.de/davie-selke_2948/","kickbaseId":"1183"},{"lastName":"Timothy Chandler","delta":-121599,"detailPageLink":"https://www.ligainsider.de/timothy-chandler_643/","kickbaseId":"461"},{"lastName":"Sergio Córdova","delta":-121498,"detailPageLink":"https://www.ligainsider.de/sergio-cordova_14181/","kickbaseId":"2083"},{"lastName":"Nils Petersen","delta":-120283,"detailPageLink":"https://www.ligainsider.de/nils-petersen_654/","kickbaseId":"317"},{"lastName":"Carlos Gruezo","delta":-119589,"detailPageLink":"https://www.ligainsider.de/carlos-gruezo_3312/","kickbaseId":"1212"},{"lastName":"Ishak Belfodil","delta":-119034,"detailPageLink":"https://www.ligainsider.de/ishak-belfodil_2429/","kickbaseId":"2153"},{"lastName":"Miloš Pantović","delta":-118944,"detailPageLink":"https://www.ligainsider.de/milos-pantovic_6885/","kickbaseId":"1794"},{"lastName":"Clinton Mola","delta":-118573,"detailPageLink":"https://www.ligainsider.de/clinton-mola_23913/","kickbaseId":"2817"},{"lastName":"Lucas Tousart","delta":-118407,"detailPageLink":"https://www.ligainsider.de/lucas-tousart_12406/","kickbaseId":"2814"},{"lastName":"László Bénes","delta":-118188,"detailPageLink":"https://www.ligainsider.de/laszlo-benes_9586/","kickbaseId":"1877"},{"lastName":"Nikolas Nartey","delta":-117839,"detailPageLink":"https://www.ligainsider.de/nikolas-nartey_13737/","kickbaseId":"2120"},{"lastName":"Iago","delta":-117660,"detailPageLink":"https://www.ligainsider.de/iago-amaral-borduchi_20626/","kickbaseId":"2662"},{"lastName":"Dominique Heintz","delta":-117623,"detailPageLink":"https://www.ligainsider.de/dominique-heintz_1669/","kickbaseId":"1249"},{"lastName":"Cédric Brunner","delta":-117412,"detailPageLink":"https://www.ligainsider.de/cedric-brunner_11557/","kickbaseId":"2429"},{"lastName":"Masaya Okugawa","delta":-114978,"detailPageLink":"https://www.ligainsider.de/masaya-okugawa_6469/","kickbaseId":"2494"},{"lastName":"Sascha Burchert","delta":-114776,"detailPageLink":"https://www.ligainsider.de/sascha-burchert_299/","kickbaseId":"697"},{"lastName":"Konstantinos Stafylidis","delta":-114697,"detailPageLink":"https://www.ligainsider.de/konstantinos-stafylidis_2280/","kickbaseId":"616"},{"lastName":"Timo Horn","delta":-113604,"detailPageLink":"https://www.ligainsider.de/timo-horn_516/","kickbaseId":"1245"},{"lastName":"Jeremy Dudziak","delta":-113530,"detailPageLink":"https://www.ligainsider.de/jeremy-dudziak_5820/","kickbaseId":"1657"},{"lastName":"Christopher Antwi-Adjei","delta":-113468,"detailPageLink":"https://www.ligainsider.de/christopher-antwi-adjei_15297/","kickbaseId":"2539"},{"lastName":"Tim Lemperle","delta":-112294,"detailPageLink":"https://www.ligainsider.de/tim-lemperle_23854/","kickbaseId":"2803"},{"lastName":"Munas Dabbur","delta":-112206,"detailPageLink":"https://www.ligainsider.de/munas-dabbur_7624/","kickbaseId":"2768"},{"lastName":"Timothy Tillman","delta":-111766,"detailPageLink":"https://www.ligainsider.de/timothy-tillman_10467/","kickbaseId":"1932"},{"lastName":"Yannik Keitel","delta":-111095,"detailPageLink":"https://www.ligainsider.de/yannik-keitel_22010/","kickbaseId":"2764"},{"lastName":"Mateu Morey","delta":-109635,"detailPageLink":"https://www.ligainsider.de/mateu-morey_14250/","kickbaseId":"2665"},{"lastName":"Sargis Adamyan","delta":-108735,"detailPageLink":"https://www.ligainsider.de/sargis-adamyan_14085/","kickbaseId":"2426"},{"lastName":"Ilaix Moriba","delta":-108281,"detailPageLink":"https://www.ligainsider.de/ilaix-moriba_25848/","kickbaseId":"3140"},{"lastName":"Anderson Lucoqui","delta":-106651,"detailPageLink":"https://www.ligainsider.de/anderson-lucoqui_7628/","kickbaseId":"2260"},{"lastName":"Paul Seguin","delta":-106294,"detailPageLink":"https://www.ligainsider.de/paul-seguin_3655/","kickbaseId":"1207"},{"lastName":"Tanguy Nianzou","delta":-105633,"detailPageLink":"https://www.ligainsider.de/tanguy-nianzou-kouassi_23744/","kickbaseId":"2823"},{"lastName":"Maximilian Bauer","delta":-105471,"detailPageLink":"https://www.ligainsider.de/maximilian-bauer_14214/","kickbaseId":"2582"},{"lastName":"Makoto Hasebe","delta":-105225,"detailPageLink":"https://www.ligainsider.de/makoto-hasebe_342/","kickbaseId":"285"},{"lastName":"Brian Brobbey","delta":-104660,"detailPageLink":"https://www.ligainsider.de/brian-brobbey_25589/","kickbaseId":"3002"},{"lastName":"Stefan Ilsanker","delta":-104281,"detailPageLink":"https://www.ligainsider.de/stefan-ilsanker_6351/","kickbaseId":"1899"},{"lastName":"Bouna Sarr","delta":-103587,"detailPageLink":"https://www.ligainsider.de/bouna-sarr_17152/","kickbaseId":"2915"},{"lastName":"Daley Sinkgraven","delta":-103080,"detailPageLink":"https://www.ligainsider.de/daley-sinkgraven_11384/","kickbaseId":"2645"},{"lastName":"Reinier","delta":-102899,"detailPageLink":"https://www.ligainsider.de/reinier-jesus-carvalho_20536/","kickbaseId":"2873"},{"lastName":"Simon Zoller","delta":-102588,"detailPageLink":"https://www.ligainsider.de/simon-zoller_2648/","kickbaseId":"1534"},{"lastName":"Tony Jantschke","delta":-102498,"detailPageLink":"https://www.ligainsider.de/tony-jantschke_304/","kickbaseId":"387"},{"lastName":"Hannes Wolf","delta":-102439,"detailPageLink":"https://www.ligainsider.de/hannes-wolf_12993/","kickbaseId":"2655"},{"lastName":"Krzysztof Piątek","delta":-101576,"detailPageLink":"https://www.ligainsider.de/krzysztof-piatek_20290/","kickbaseId":"2780"},{"lastName":"Felix Nmecha","delta":-101319,"detailPageLink":"https://www.ligainsider.de/felix-nmecha_25090/","kickbaseId":"3069"},{"lastName":"Fabian Bredlow","delta":-101260,"detailPageLink":"https://www.ligainsider.de/fabian-bredlow_6395/","kickbaseId":"2237"},{"lastName":"Felix Uduokhai","delta":-100881,"detailPageLink":"https://www.ligainsider.de/ohis-felix-uduokhai_7041/","kickbaseId":"2065"},{"lastName":"Pascal Stenzel","delta":-99615,"detailPageLink":"https://www.ligainsider.de/pascal-stenzel_6002/","kickbaseId":"1758"},{"lastName":"Karim Bellarabi","delta":-99255,"detailPageLink":"https://www.ligainsider.de/karim-bellarabi_676/","kickbaseId":"486"},{"lastName":"Patrick Wimmer","delta":-98668,"detailPageLink":"https://www.ligainsider.de/patrick-wimmer_26236/","kickbaseId":"3124"},{"lastName":"Maxim Leitsch","delta":-98622,"detailPageLink":"https://www.ligainsider.de/maxim-leitsch_10606/","kickbaseId":"2515"},{"lastName":"Kingsley Ehizibue","delta":-97383,"detailPageLink":"https://www.ligainsider.de/kingsley-ehizibue_20599/","kickbaseId":"2648"},{"lastName":"Amos Pieper","delta":-97098,"detailPageLink":"https://www.ligainsider.de/amos-pieper_7061/","kickbaseId":"2294"},{"lastName":"Joško Gvardiol","delta":-97029,"detailPageLink":"https://www.ligainsider.de/josko-gvardiol_23402/","kickbaseId":"3003"},{"lastName":"Christopher Lenz","delta":-96372,"detailPageLink":"https://www.ligainsider.de/christopher-lenz_2123/","kickbaseId":"1739"},{"lastName":"Maxence Lacroix","delta":-95487,"detailPageLink":"https://www.ligainsider.de/maxence-lacroix_24609/","kickbaseId":"2878"},{"lastName":"Stevan Jovetić","delta":-95033,"detailPageLink":"https://www.ligainsider.de/stevan-jovetic_4756/","kickbaseId":"3088"},{"lastName":"Danny da Costa","delta":-94593,"detailPageLink":"https://www.ligainsider.de/danny-da-costa_650/","kickbaseId":"1540"},{"lastName":"Benjamin Henrichs","delta":-94099,"detailPageLink":"https://www.ligainsider.de/benjamin-henrichs_5680/","kickbaseId":"1689"},{"lastName":"Ádám Szalai","delta":-94081,"detailPageLink":"https://www.ligainsider.de/adam-szalai_403/","kickbaseId":"463"},{"lastName":"Janik Haberer","delta":-92208,"detailPageLink":"https://www.ligainsider.de/janik-haberer_3616/","kickbaseId":"1553"},{"lastName":"Daniel Brosinski","delta":-92122,"detailPageLink":"https://www.ligainsider.de/daniel-brosinski_955/","kickbaseId":"377"},{"lastName":"Joakim Nilsson","delta":-91733,"detailPageLink":"https://www.ligainsider.de/joakim-nilsson_20934/","kickbaseId":"2812"},{"lastName":"Marcel Halstenberg","delta":-91239,"detailPageLink":"https://www.ligainsider.de/marcel-halstenberg_2436/","kickbaseId":"77"},{"lastName":"Hans Nunoo Sarpei","delta":-90087,"detailPageLink":"https://www.ligainsider.de/hans-nunoo-sarpei_10674/","kickbaseId":"2071"},{"lastName":"Almamy Touré","delta":-89369,"detailPageLink":"https://www.ligainsider.de/almamy-toure_12425/","kickbaseId":"2376"},{"lastName":"Robin Hack","delta":-88696,"detailPageLink":"https://www.ligainsider.de/robin-hack_14139/","kickbaseId":"2074"},{"lastName":"Ragnar Ache","delta":-88183,"detailPageLink":"https://www.ligainsider.de/ragnar-ache_23720/","kickbaseId":"2855"},{"lastName":"Niklas Dorsch","delta":-87838,"detailPageLink":"https://www.ligainsider.de/niklas-dorsch_6811/","kickbaseId":"1929"},{"lastName":"Philipp Förster","delta":-87107,"detailPageLink":"https://www.ligainsider.de/philipp-foerster_12975/","kickbaseId":"2526"},{"lastName":"Erik Thommy","delta":-86404,"detailPageLink":"https://www.ligainsider.de/erik-thommy_3307/","kickbaseId":"1208"},{"lastName":"Jan Thielmann","delta":-84641,"detailPageLink":"https://www.ligainsider.de/jan-thielmann_21998/","kickbaseId":"2765"},{"lastName":"Mads Pedersen","delta":-84168,"detailPageLink":"https://www.ligainsider.de/mads-pedersen_15841/","kickbaseId":"2651"},{"lastName":"Gonçalo Paciência","delta":-81719,"detailPageLink":"https://www.ligainsider.de/goncalo-paciencia_12176/","kickbaseId":"2287"},{"lastName":"Robert Gumny","delta":-81548,"detailPageLink":"https://www.ligainsider.de/robert-gumny_18666/","kickbaseId":"2885"},{"lastName":"Maximilian Philipp","delta":-78932,"detailPageLink":"https://www.ligainsider.de/maximilian-philipp_2246/","kickbaseId":"1226"},{"lastName":"Christoph Kramer","delta":-78670,"detailPageLink":"https://www.ligainsider.de/christoph-kramer_1465/","kickbaseId":"8"},{"lastName":"Benjamin Hübner","delta":-76859,"detailPageLink":"https://www.ligainsider.de/benjamin-huebner_5731/","kickbaseId":"1429"},{"lastName":"Roland Sallai","delta":-76569,"detailPageLink":"https://www.ligainsider.de/roland-sallai_8054/","kickbaseId":"2343"},{"lastName":"Philipp Klement","delta":-75876,"detailPageLink":"https://www.ligainsider.de/philipp-klement_1455/","kickbaseId":"6"},{"lastName":"Gerrit Holtmann","delta":-75720,"detailPageLink":"https://www.ligainsider.de/gerrit-holtmann_6352/","kickbaseId":"1881"},{"lastName":"Jorge Meré","delta":-75439,"detailPageLink":"https://www.ligainsider.de/jorge-mere_8921/","kickbaseId":"2118"},{"lastName":"Patrick Herrmann","delta":-74506,"detailPageLink":"https://www.ligainsider.de/patrick-herrmann_387/","kickbaseId":"547"},{"lastName":"Mateo Klimowicz","delta":-73639,"detailPageLink":"https://www.ligainsider.de/mateo-klimowicz_20541/","kickbaseId":"2818"},{"lastName":"Deyovaisio Zeefuik","delta":-72141,"detailPageLink":"https://www.ligainsider.de/deyovaisio-zeefuik_24123/","kickbaseId":"2867"},{"lastName":"Andreas Voglsammer","delta":-71110,"detailPageLink":"https://www.ligainsider.de/andreas-voglsammer_6233/","kickbaseId":"2631"},{"lastName":"Alessandro Schöpf","delta":-70535,"detailPageLink":"https://www.ligainsider.de/alessandro-schoepf_2730/","kickbaseId":"1230"},{"lastName":"Manuel Prietl","delta":-67076,"detailPageLink":"https://www.ligainsider.de/manuel-prietl_9584/","kickbaseId":"2416"},{"lastName":"Timo Hübers","delta":-64636,"detailPageLink":"https://www.ligainsider.de/timo-huebers_8912/","kickbaseId":"2069"},{"lastName":"Dan-Axel Zagadou","delta":-64205,"detailPageLink":"https://www.ligainsider.de/dan-axel-zagadou_12683/","kickbaseId":"2068"},{"lastName":"Ermedin Demirović","delta":-64181,"detailPageLink":"https://www.ligainsider.de/ermedin-demirovic_24166/","kickbaseId":"2854"},{"lastName":"Alexander Schwolow","delta":-58589,"detailPageLink":"https://www.ligainsider.de/alexander-schwolow_1781/","kickbaseId":"620"},{"lastName":"Moussa Diaby","delta":-55036,"detailPageLink":"https://www.ligainsider.de/moussa-diaby_20616/","kickbaseId":"2661"},{"lastName":"Ansgar Knauff","delta":-52968,"detailPageLink":"https://www.ligainsider.de/ansgar-knauff_24398/","kickbaseId":"2863"},{"lastName":"Florian Niederlechner","delta":-52457,"detailPageLink":"https://www.ligainsider.de/florian-niederlechner_5778/","kickbaseId":"1680"},{"lastName":"Angelo Stiller","delta":-50192,"detailPageLink":"https://www.ligainsider.de/angelo-stiller_20766/","kickbaseId":"2694"},{"lastName":"Roberto Massimo","delta":-47478,"detailPageLink":"https://www.ligainsider.de/roberto-massimo_18407/","kickbaseId":"2546"},{"lastName":"Janni Serra","delta":-45326,"detailPageLink":"https://www.ligainsider.de/janni-serra_6836/","kickbaseId":"2474"},{"lastName":"Arne Maier","delta":-40700,"detailPageLink":"https://www.ligainsider.de/arne-maier_10422/","kickbaseId":"2005"},{"lastName":"Ajdin Hrustić","delta":-40622,"detailPageLink":"https://www.ligainsider.de/ajdin-hrustic_24639/","kickbaseId":"2908"},{"lastName":"Sebastiaan Bornauw","delta":-39104,"detailPageLink":"https://www.ligainsider.de/sebastiaan-bornauw_18822/","kickbaseId":"2725"},{"lastName":"Grischa Prömel","delta":-38013,"detailPageLink":"https://www.ligainsider.de/grischa-proemel_5816/","kickbaseId":"1671"},{"lastName":"Edimilson Fernandes","delta":-36892,"detailPageLink":"https://www.ligainsider.de/edimilson-fernandes_7666/","kickbaseId":"2643"},{"lastName":"Aymen Barkok","delta":-31667,"detailPageLink":"https://www.ligainsider.de/aymen-barkok_12576/","kickbaseId":"1971"},{"lastName":"Vladimír Darida","delta":-28580,"detailPageLink":"https://www.ligainsider.de/vladimir-darida_2428/","kickbaseId":"748"},{"lastName":"Kevin Behrens","delta":-27513,"detailPageLink":"https://www.ligainsider.de/kevin-behrens_14742/","kickbaseId":"2496"},{"lastName":"Kiliann Sildillia","delta":-26189,"detailPageLink":"https://www.ligainsider.de/kiliann-sildillia_24158/","kickbaseId":"2946"},{"lastName":"Joe Scally","delta":-22553,"detailPageLink":"https://www.ligainsider.de/joe-scally_23700/","kickbaseId":"2941"},{"lastName":"Piero Hincapié","delta":-19610,"detailPageLink":"https://www.ligainsider.de/piero-hincapie_26475/","kickbaseId":"3128"},{"lastName":"Julian Ryerson","delta":-17682,"detailPageLink":"https://www.ligainsider.de/julian-ryerson_18478/","kickbaseId":"2395"},{"lastName":"Kevin Schade","delta":-11940,"detailPageLink":"https://www.ligainsider.de/kevin-schade_24157/","kickbaseId":"2930"},{"lastName":"Fabian Kunze","delta":-8990,"detailPageLink":"https://www.ligainsider.de/fabian-kunze_19820/","kickbaseId":"2821"}]}